[
    {
        "生产性服务业大类": "01",
        "生产性服务业大类名称": "研发设计与其他技术服务",
        "生产性服务业中类": "011",
        "生产性服务业中类名称": "研发与设计服务",
        "生产性服务业小类": "0111",
        "生产性服务业小类名称": "生产性自然科学研究和试验发展",
        "说明": "  指直接应用于生产活动的数学研究、信息科学与系统科学、化学、生物学等科学研究服务",
        "国民经济行业代码": "7310*",
        "国民经济行业名称": ""
    },
    {
        "生产性服务业大类": "01",
        "生产性服务业大类名称": "研发设计与其他技术服务",
        "生产性服务业中类": "011",
        "生产性服务业中类名称": "研发与设计服务",
        "生产性服务业小类": "0112",
        "生产性服务业小类名称": "工程和技术研究和试验发展",
        "说明": "  指工程和技术基础科学研究、测绘科学技术研究、材料科学研究、冶金工程技术研究、机械工程研究等工程和技术研究，新材料研发、新产品研发、新工艺研发等包含在此类",
        "国民经济行业代码": 7320,
        "国民经济行业名称": ""
    },
    {
        "生产性服务业大类": "01",
        "生产性服务业大类名称": "研发设计与其他技术服务",
        "生产性服务业中类": "011",
        "生产性服务业中类名称": "研发与设计服务",
        "生产性服务业小类": "0113",
        "生产性服务业小类名称": "农业科学研究和试验发展",
        "说明": "  指农学研究，林学研究，畜牧、兽医研究，水产学研究及其他农业科学研究与试验发展",
        "国民经济行业代码": 7330,
        "国民经济行业名称": ""
    },
    {
        "生产性服务业大类": "01",
        "生产性服务业大类名称": "研发设计与其他技术服务",
        "生产性服务业中类": "011",
        "生产性服务业中类名称": "研发与设计服务",
        "生产性服务业小类": "0114",
        "生产性服务业小类名称": "生产性医学研究和试验发展",
        "说明": "  指直接用于生产活动的医学、药学、中医学与中药学、运动医学等研究与试验发展",
        "国民经济行业代码": "7340*",
        "国民经济行业名称": ""
    },
    {
        "生产性服务业大类": "01",
        "生产性服务业大类名称": "研发设计与其他技术服务",
        "生产性服务业中类": "011",
        "生产性服务业中类名称": "研发与设计服务",
        "生产性服务业小类": "0115",
        "生产性服务业小类名称": "工业设计服务",
        "说明": "  指独立于生产企业的工业产品和生产工艺设计；不包括工业产品生产环境设计、产品传播设计、产品设计管理等活动",
        "国民经济行业代码": 7491,
        "国民经济行业名称": ""
    },
    {
        "生产性服务业大类": "01",
        "生产性服务业大类名称": "研发设计与其他技术服务",
        "生产性服务业中类": "011",
        "生产性服务业中类名称": "研发与设计服务",
        "生产性服务业小类": "0116",
        "生产性服务业小类名称": "专业设计服务",
        "说明": "  指除工程设计、软件设计、集成电路设计、工业设计以外的各种专业设计服务",
        "国民经济行业代码": 7492,
        "国民经济行业名称": ""
    },
    {
        "生产性服务业大类": "01",
        "生产性服务业大类名称": "研发设计与其他技术服务",
        "生产性服务业中类": "012",
        "生产性服务业中类名称": "科技成果转化服务",
        "生产性服务业小类": "0121",
        "生产性服务业小类名称": "农林牧渔技术推广服务",
        "说明": "  指为解决农业研究与试验发展活动产生的新技术、新工艺、新产品能投入生产或在实际应用中存在的技术问题而进行的系统性活动，种植技术、畜禽饲养技术、水产养殖技术、农机化技术及其他农业技术的开发、咨询、交流、转让、推广服务，农业废弃物资源化利用技术推广服务",
        "国民经济行业代码": 7511,
        "国民经济行业名称": ""
    },
    {
        "生产性服务业大类": "01",
        "生产性服务业大类名称": "研发设计与其他技术服务",
        "生产性服务业中类": "012",
        "生产性服务业中类名称": "科技成果转化服务",
        "生产性服务业小类": "0122",
        "生产性服务业小类名称": "生物技术推广服务",
        "说明": "  指为解决生物工程的研究与试验发展活动产生的新技术、新工艺、新产品能投入生产或在实际应用中存在的技术问题而进行的系统性活动，生物工程技术开发、咨询、交流、转让、推广服务",
        "国民经济行业代码": 7512,
        "国民经济行业名称": ""
    },
    {
        "生产性服务业大类": "01",
        "生产性服务业大类名称": "研发设计与其他技术服务",
        "生产性服务业中类": "012",
        "生产性服务业中类名称": "科技成果转化服务",
        "生产性服务业小类": "0123",
        "生产性服务业小类名称": "新材料技术推广服务",
        "说明": "  指为解决新材料技术工程的研究与试验发展活动产生的新技术、新工艺、新产品能投入生产或在实际应用中存在的技术问题而进行的系统性活动，新材料技术开发、咨询、交流、转让、推广服务",
        "国民经济行业代码": 7513,
        "国民经济行业名称": ""
    },
    {
        "生产性服务业大类": "01",
        "生产性服务业大类名称": "研发设计与其他技术服务",
        "生产性服务业中类": "012",
        "生产性服务业中类名称": "科技成果转化服务",
        "生产性服务业小类": "0124",
        "生产性服务业小类名称": "新能源技术推广服务",
        "说明": "  指为解决新能源技术工程的研究与试验发展活动产生的新技术、新工艺、新产品能投入生产或在实际应用中存在的技术问题而进行的系统性活动，风能、太阳能、核能、生物质能和其他新能源技术开发、咨询、交流、转让、推广服务",
        "国民经济行业代码": 7515,
        "国民经济行业名称": ""
    },
    {
        "生产性服务业大类": "01",
        "生产性服务业大类名称": "研发设计与其他技术服务",
        "生产性服务业中类": "012",
        "生产性服务业中类名称": "科技成果转化服务",
        "生产性服务业小类": "0125",
        "生产性服务业小类名称": "三维（3D）打印技术推广服务",
        "说明": "  指为解决三维（3D）打印技术工程的研究与试验发展活动产生的新技术、新工艺、新产品能投入生产或在实际应用中存在的技术问题而进行的系统性活动，三维（3D）打印技术开发、咨询、交流、转让、推广和打印服务",
        "国民经济行业代码": 7517,
        "国民经济行业名称": ""
    },
    {
        "生产性服务业大类": "01",
        "生产性服务业大类名称": "研发设计与其他技术服务",
        "生产性服务业中类": "012",
        "生产性服务业中类名称": "科技成果转化服务",
        "生产性服务业小类": "0126",
        "生产性服务业小类名称": "其他生产性技术推广服务",
        "说明": "  指社会公益有关的技术推广、扩散和转移的活动，以技术推广为主的技（科）、工、贸联合公司的活动及其他技术开发、咨询、交流、转让、推广服务；不包括节能技术推广服务和环保技术推广服务",
        "国民经济行业代码": "7519*",
        "国民经济行业名称": ""
    },
    {
        "生产性服务业大类": "01",
        "生产性服务业大类名称": "研发设计与其他技术服务",
        "生产性服务业中类": "012",
        "生产性服务业中类名称": "科技成果转化服务",
        "生产性服务业小类": "0127",
        "生产性服务业小类名称": "科技中介服务",
        "说明": "  指为科技活动提供社会化服务与管理，在政府、各类科技活动主体与市场之间提供居间服务的组织，主要开展信息交流、技术咨询、科技评估和科技鉴证等活动，科技评估和鉴证、科技信息交流、技术咨询等包含在此类",
        "国民经济行业代码": 7530,
        "国民经济行业名称": ""
    },
    {
        "生产性服务业大类": "01",
        "生产性服务业大类名称": "研发设计与其他技术服务",
        "生产性服务业中类": "012",
        "生产性服务业中类名称": "科技成果转化服务",
        "生产性服务业小类": "0128",
        "生产性服务业小类名称": "创业空间服务",
        "说明": "  指顺应新科技革命和产业变革新趋势、有效满足网络时代大众创业创新需求的新型创业服务平台，它是针对早期创业的重要服务载体，主要为创业者提供低成本的工作空间、网络空间、社交空间和资源共享空间，包括众创空间、孵化器、创业基地等，创业、创新扶持服务、科技孵化器等包含在此类",
        "国民经济行业代码": 7540,
        "国民经济行业名称": ""
    },
    {
        "生产性服务业大类": "01",
        "生产性服务业大类名称": "研发设计与其他技术服务",
        "生产性服务业中类": "012",
        "生产性服务业中类名称": "科技成果转化服务",
        "生产性服务业小类": "0129",
        "生产性服务业小类名称": "其他科技推广服务业",
        "说明": "  指除技术推广、科技中介以外的其他科技服务，不包括短期的日常业务活动",
        "国民经济行业代码": 7590,
        "国民经济行业名称": ""
    },
    {
        "生产性服务业大类": "01",
        "生产性服务业大类名称": "研发设计与其他技术服务",
        "生产性服务业中类": "013",
        "生产性服务业中类名称": "知识产权及相关法律服务",
        "生产性服务业小类": "0131",
        "生产性服务业小类名称": "知识产权服务",
        "说明": "  指专利、商标、版权、软件、集成电路布图设计、技术秘密、地理标志等各类知识产权的代理、转让、登记、鉴定、检索、分析、咨询、评估、运营、认证等服务",
        "国民经济行业代码": 7520,
        "国民经济行业名称": ""
    },
    {
        "生产性服务业大类": "01",
        "生产性服务业大类名称": "研发设计与其他技术服务",
        "生产性服务业中类": "013",
        "生产性服务业中类名称": "知识产权及相关法律服务",
        "生产性服务业小类": "0131",
        "生产性服务业小类名称": "知识产权服务",
        "说明": "  指专利、商标、版权、软件、集成电路布图设计、技术秘密、地理标志等各类知识产权的代理、转让、登记、鉴定、检索、分析、咨询、评估、运营、认证等服务",
        "国民经济行业代码": 7520,
        "国民经济行业名称": ""
    },
    {
        "生产性服务业大类": "01",
        "生产性服务业大类名称": "研发设计与其他技术服务",
        "生产性服务业中类": "013",
        "生产性服务业中类名称": "知识产权及相关法律服务",
        "生产性服务业小类": "0132",
        "生产性服务业小类名称": "生产性法律服务",
        "说明": "  指为生产活动提供的律师、公证、仲裁、调解等其他法律服务活动",
        "国民经济行业代码": "723*",
        "国民经济行业名称": ""
    },
    {
        "生产性服务业大类": "01",
        "生产性服务业大类名称": "研发设计与其他技术服务",
        "生产性服务业中类": "013",
        "生产性服务业中类名称": "知识产权及相关法律服务",
        "生产性服务业小类": "0132",
        "生产性服务业小类名称": "生产性法律服务",
        "说明": "  指为生产活动提供的律师、公证、仲裁、调解等其他法律服务活动",
        "国民经济行业代码": "723*",
        "国民经济行业名称": ""
    },
    {
        "生产性服务业大类": "01",
        "生产性服务业大类名称": "研发设计与其他技术服务",
        "生产性服务业中类": "014",
        "生产性服务业中类名称": "检验检测认证标准计量服务",
        "生产性服务业小类": "0140",
        "生产性服务业小类名称": "质检技术服务",
        "说明": "  指通过专业技术手段对动植物、工业产品、商品、专项技术、成果及其他需要鉴定的物品、服务、管理体系、人员能力等所进行的检测、检验、检疫、测试、鉴定等活动，还包括产品质量、标准、计量、认证认可等活动，第三方检验、检测、测试、分析、认证、计量和标准活动包括在此类",
        "国民经济行业代码": 745,
        "国民经济行业名称": ""
    },
    {
        "生产性服务业大类": "01",
        "生产性服务业大类名称": "研发设计与其他技术服务",
        "生产性服务业中类": "015",
        "生产性服务业中类名称": "生产性专业技术服务",
        "生产性服务业小类": "0151",
        "生产性服务业小类名称": "生产性气象服务 ",
        "说明": "  指用于生产活动的气象服务",
        "国民经济行业代码": "7410*",
        "国民经济行业名称": ""
    },
    {
        "生产性服务业大类": "01",
        "生产性服务业大类名称": "研发设计与其他技术服务",
        "生产性服务业中类": "015",
        "生产性服务业中类名称": "生产性专业技术服务",
        "生产性服务业小类": "0152",
        "生产性服务业小类名称": "生产性地震服务 ",
        "说明": "  指用于生产活动的地震服务",
        "国民经济行业代码": "7420*",
        "国民经济行业名称": ""
    },
    {
        "生产性服务业大类": "01",
        "生产性服务业大类名称": "研发设计与其他技术服务",
        "生产性服务业中类": "015",
        "生产性服务业中类名称": "生产性专业技术服务",
        "生产性服务业小类": "0153",
        "生产性服务业小类名称": "生产性海洋服务 ",
        "说明": "  指用于生产活动的海洋服务",
        "国民经济行业代码": "743*",
        "国民经济行业名称": ""
    },
    {
        "生产性服务业大类": "01",
        "生产性服务业大类名称": "研发设计与其他技术服务",
        "生产性服务业中类": "015",
        "生产性服务业中类名称": "生产性专业技术服务",
        "生产性服务业小类": "0154",
        "生产性服务业小类名称": "生产性测绘服务 ",
        "说明": "  指用于生产活动的测绘服务",
        "国民经济行业代码": "744*",
        "国民经济行业名称": ""
    },
    {
        "生产性服务业大类": "01",
        "生产性服务业大类名称": "研发设计与其他技术服务",
        "生产性服务业中类": "015",
        "生产性服务业中类名称": "生产性专业技术服务",
        "生产性服务业小类": "0155",
        "生产性服务业小类名称": "地质勘查服务",
        "说明": "  指对矿产资源、工程地质、科学研究进行的地质勘查、测试、监测、评估等活动",
        "国民经济行业代码": 747,
        "国民经济行业名称": ""
    },
    {
        "生产性服务业大类": "01",
        "生产性服务业大类名称": "研发设计与其他技术服务",
        "生产性服务业中类": "015",
        "生产性服务业中类名称": "生产性专业技术服务",
        "生产性服务业小类": "0156",
        "生产性服务业小类名称": "工程管理服务",
        "说明": "  指工程项目建设中的项目策划、投资与造价咨询、招标代理、项目管理等服务",
        "国民经济行业代码": 7481,
        "国民经济行业名称": ""
    },
    {
        "生产性服务业大类": "01",
        "生产性服务业大类名称": "研发设计与其他技术服务",
        "生产性服务业中类": "015",
        "生产性服务业中类名称": "生产性专业技术服务",
        "生产性服务业小类": "0157",
        "生产性服务业小类名称": "工程监理服务",
        "说明": "  指依照法律、行政法规及有关的技术标准、设计文件和建筑工程承包合同，对承包单位在施工质量、建设工期和建设资金使用等方面，代表建设单位实施监理的服务",
        "国民经济行业代码": 7482,
        "国民经济行业名称": ""
    },
    {
        "生产性服务业大类": "01",
        "生产性服务业大类名称": "研发设计与其他技术服务",
        "生产性服务业中类": "015",
        "生产性服务业中类名称": "生产性专业技术服务",
        "生产性服务业小类": "0158",
        "生产性服务业小类名称": "其他生产性专业技术服务",
        "说明": "  指为生产提供的生态资源监测、野生动物疫源疫病防控监测，工程勘察活动、工程设计活动、规划设计管理、土地规划服务和其他未列明专业技术服务",
        "国民经济行业代码": "7462*",
        "国民经济行业名称": ""
    },
    {
        "生产性服务业大类": "01",
        "生产性服务业大类名称": "研发设计与其他技术服务",
        "生产性服务业中类": "015",
        "生产性服务业中类名称": "生产性专业技术服务",
        "生产性服务业小类": "0158",
        "生产性服务业小类名称": "其他生产性专业技术服务",
        "说明": "  指为生产提供的生态资源监测、野生动物疫源疫病防控监测，工程勘察活动、工程设计活动、规划设计管理、土地规划服务和其他未列明专业技术服务",
        "国民经济行业代码": "7463*",
        "国民经济行业名称": ""
    },
    {
        "生产性服务业大类": "01",
        "生产性服务业大类名称": "研发设计与其他技术服务",
        "生产性服务业中类": "015",
        "生产性服务业中类名称": "生产性专业技术服务",
        "生产性服务业小类": "0158",
        "生产性服务业小类名称": "其他生产性专业技术服务",
        "说明": "  指为生产提供的生态资源监测、野生动物疫源疫病防控监测，工程勘察活动、工程设计活动、规划设计管理、土地规划服务和其他未列明专业技术服务",
        "国民经济行业代码": 7483,
        "国民经济行业名称": ""
    },
    {
        "生产性服务业大类": "01",
        "生产性服务业大类名称": "研发设计与其他技术服务",
        "生产性服务业中类": "015",
        "生产性服务业中类名称": "生产性专业技术服务",
        "生产性服务业小类": "0158",
        "生产性服务业小类名称": "其他生产性专业技术服务",
        "说明": "  指为生产提供的生态资源监测、野生动物疫源疫病防控监测，工程勘察活动、工程设计活动、规划设计管理、土地规划服务和其他未列明专业技术服务",
        "国民经济行业代码": 7484,
        "国民经济行业名称": ""
    },
    {
        "生产性服务业大类": "01",
        "生产性服务业大类名称": "研发设计与其他技术服务",
        "生产性服务业中类": "015",
        "生产性服务业中类名称": "生产性专业技术服务",
        "生产性服务业小类": "0158",
        "生产性服务业小类名称": "其他生产性专业技术服务",
        "说明": "  指为生产提供的生态资源监测、野生动物疫源疫病防控监测，工程勘察活动、工程设计活动、规划设计管理、土地规划服务和其他未列明专业技术服务",
        "国民经济行业代码": 7485,
        "国民经济行业名称": ""
    },
    {
        "生产性服务业大类": "01",
        "生产性服务业大类名称": "研发设计与其他技术服务",
        "生产性服务业中类": "015",
        "生产性服务业中类名称": "生产性专业技术服务",
        "生产性服务业小类": "0158",
        "生产性服务业小类名称": "其他生产性专业技术服务",
        "说明": "  指为生产提供的生态资源监测、野生动物疫源疫病防控监测，工程勘察活动、工程设计活动、规划设计管理、土地规划服务和其他未列明专业技术服务",
        "国民经济行业代码": 7486,
        "国民经济行业名称": ""
    },
    {
        "生产性服务业大类": "01",
        "生产性服务业大类名称": "研发设计与其他技术服务",
        "生产性服务业中类": "015",
        "生产性服务业中类名称": "生产性专业技术服务",
        "生产性服务业小类": "0158",
        "生产性服务业小类名称": "其他生产性专业技术服务",
        "说明": "  指为生产提供的生态资源监测、野生动物疫源疫病防控监测，工程勘察活动、工程设计活动、规划设计管理、土地规划服务和其他未列明专业技术服务",
        "国民经济行业代码": 7493,
        "国民经济行业名称": ""
    },
    {
        "生产性服务业大类": "01",
        "生产性服务业大类名称": "研发设计与其他技术服务",
        "生产性服务业中类": "015",
        "生产性服务业中类名称": "生产性专业技术服务",
        "生产性服务业小类": "0158",
        "生产性服务业小类名称": "其他生产性专业技术服务",
        "说明": "  指为生产提供的生态资源监测、野生动物疫源疫病防控监测，工程勘察活动、工程设计活动、规划设计管理、土地规划服务和其他未列明专业技术服务",
        "国民经济行业代码": 7499,
        "国民经济行业名称": ""
    },
    {
        "生产性服务业大类": "02",
        "生产性服务业大类名称": "货物运输、通用航空生产、仓储和邮政快递服务",
        "生产性服务业中类": "021",
        "生产性服务业中类名称": "货物运输服务",
        "生产性服务业小类": "0211",
        "生产性服务业小类名称": "铁路货物运输",
        "说明": "  指专门从事铁路货物运输的活动",
        "国民经济行业代码": 5320,
        "国民经济行业名称": ""
    },
    {
        "生产性服务业大类": "02",
        "生产性服务业大类名称": "货物运输、通用航空生产、仓储和邮政快递服务",
        "生产性服务业中类": "021",
        "生产性服务业中类名称": "货物运输服务",
        "生产性服务业小类": "0212",
        "生产性服务业小类名称": "道路货物运输",
        "说明": "  指所有道路的货物运输活动",
        "国民经济行业代码": 543,
        "国民经济行业名称": ""
    },
    {
        "生产性服务业大类": "02",
        "生产性服务业大类名称": "货物运输、通用航空生产、仓储和邮政快递服务",
        "生产性服务业中类": "021",
        "生产性服务业中类名称": "货物运输服务",
        "生产性服务业小类": "0213",
        "生产性服务业小类名称": "水上货物运输",
        "说明": "  指远洋货物运输、沿海货物运输、内河货物运输",
        "国民经济行业代码": 552,
        "国民经济行业名称": ""
    },
    {
        "生产性服务业大类": "02",
        "生产性服务业大类名称": "货物运输、通用航空生产、仓储和邮政快递服务",
        "生产性服务业中类": "021",
        "生产性服务业中类名称": "货物运输服务",
        "生产性服务业小类": "0214",
        "生产性服务业小类名称": "航空货物运输",
        "说明": "  指以货物或邮件为主的航空运输活动",
        "国民经济行业代码": 5612,
        "国民经济行业名称": ""
    },
    {
        "生产性服务业大类": "02",
        "生产性服务业大类名称": "货物运输、通用航空生产、仓储和邮政快递服务",
        "生产性服务业中类": "021",
        "生产性服务业中类名称": "货物运输服务",
        "生产性服务业小类": "0215",
        "生产性服务业小类名称": "管道运输业",
        "说明": "  指通过海底管道和陆地管道对气体、液体等的运输活动",
        "国民经济行业代码": 57,
        "国民经济行业名称": ""
    },
    {
        "生产性服务业大类": "02",
        "生产性服务业大类名称": "货物运输、通用航空生产、仓储和邮政快递服务",
        "生产性服务业中类": "022",
        "生产性服务业中类名称": "货物运输辅助服务",
        "生产性服务业小类": "0221",
        "生产性服务业小类名称": "铁路货物运输辅助活动",
        "说明": "  指专门从事货物运输服务的火车站、车辆运用及维护、线桥遂涵运用及维护、牵引供电运用及维护、通信信号运用及维护、铁路专用线运用及维护和其他铁路运输辅助活动",
        "国民经济行业代码": 5332,
        "国民经济行业名称": ""
    },
    {
        "生产性服务业大类": "02",
        "生产性服务业大类名称": "货物运输、通用航空生产、仓储和邮政快递服务",
        "生产性服务业中类": "022",
        "生产性服务业中类名称": "货物运输辅助服务",
        "生产性服务业小类": "0221",
        "生产性服务业小类名称": "铁路货物运输辅助活动",
        "说明": "  指专门从事货物运输服务的火车站、车辆运用及维护、线桥遂涵运用及维护、牵引供电运用及维护、通信信号运用及维护、铁路专用线运用及维护和其他铁路运输辅助活动",
        "国民经济行业代码": 5333,
        "国民经济行业名称": ""
    },
    {
        "生产性服务业大类": "02",
        "生产性服务业大类名称": "货物运输、通用航空生产、仓储和邮政快递服务",
        "生产性服务业中类": "022",
        "生产性服务业中类名称": "货物运输辅助服务",
        "生产性服务业小类": "0221",
        "生产性服务业小类名称": "铁路货物运输辅助活动",
        "说明": "  指专门从事货物运输服务的火车站、车辆运用及维护、线桥遂涵运用及维护、牵引供电运用及维护、通信信号运用及维护、铁路专用线运用及维护和其他铁路运输辅助活动",
        "国民经济行业代码": 5339,
        "国民经济行业名称": ""
    },
    {
        "生产性服务业大类": "02",
        "生产性服务业大类名称": "货物运输、通用航空生产、仓储和邮政快递服务",
        "生产性服务业中类": "022",
        "生产性服务业中类名称": "货物运输辅助服务",
        "生产性服务业小类": "0222",
        "生产性服务业小类名称": "道路货物运输辅助活动",
        "说明": "  指以货物运输中转为目的的货物临时停放场地、公路管理与养护，其他为生产提供的道路运输辅助活动；不包括为居民提供的停车服务",
        "国民经济行业代码": 5442,
        "国民经济行业名称": ""
    },
    {
        "生产性服务业大类": "02",
        "生产性服务业大类名称": "货物运输、通用航空生产、仓储和邮政快递服务",
        "生产性服务业中类": "022",
        "生产性服务业中类名称": "货物运输辅助服务",
        "生产性服务业小类": "0222",
        "生产性服务业小类名称": "道路货物运输辅助活动",
        "说明": "  指以货物运输中转为目的的货物临时停放场地、公路管理与养护，其他为生产提供的道路运输辅助活动；不包括为居民提供的停车服务",
        "国民经济行业代码": 5443,
        "国民经济行业名称": ""
    },
    {
        "生产性服务业大类": "02",
        "生产性服务业大类名称": "货物运输、通用航空生产、仓储和邮政快递服务",
        "生产性服务业中类": "022",
        "生产性服务业中类名称": "货物运输辅助服务",
        "生产性服务业小类": "0222",
        "生产性服务业小类名称": "道路货物运输辅助活动",
        "说明": "  指以货物运输中转为目的的货物临时停放场地、公路管理与养护，其他为生产提供的道路运输辅助活动；不包括为居民提供的停车服务",
        "国民经济行业代码": "5449*",
        "国民经济行业名称": ""
    },
    {
        "生产性服务业大类": "02",
        "生产性服务业大类名称": "货物运输、通用航空生产、仓储和邮政快递服务",
        "生产性服务业中类": "022",
        "生产性服务业中类名称": "货物运输辅助服务",
        "生产性服务业小类": "0223",
        "生产性服务业小类名称": "水上货物运输辅助活动",
        "说明": "  指货运港口的管理活动和其他未列明的水上运输辅助活动",
        "国民经济行业代码": 5532,
        "国民经济行业名称": ""
    },
    {
        "生产性服务业大类": "02",
        "生产性服务业大类名称": "货物运输、通用航空生产、仓储和邮政快递服务",
        "生产性服务业中类": "022",
        "生产性服务业中类名称": "货物运输辅助服务",
        "生产性服务业小类": "0223",
        "生产性服务业小类名称": "水上货物运输辅助活动",
        "说明": "  指货运港口的管理活动和其他未列明的水上运输辅助活动",
        "国民经济行业代码": 5539,
        "国民经济行业名称": ""
    },
    {
        "生产性服务业大类": "02",
        "生产性服务业大类名称": "货物运输、通用航空生产、仓储和邮政快递服务",
        "生产性服务业中类": "022",
        "生产性服务业中类名称": "货物运输辅助服务",
        "生产性服务业小类": "0224",
        "生产性服务业小类名称": "航空货物运输辅助活动",
        "说明": "  指机场向航空公司等服务对象提供的服务活动，空中交通管理活动和其他航空运输辅助活动",
        "国民经济行业代码": "5631*",
        "国民经济行业名称": ""
    },
    {
        "生产性服务业大类": "02",
        "生产性服务业大类名称": "货物运输、通用航空生产、仓储和邮政快递服务",
        "生产性服务业中类": "022",
        "生产性服务业中类名称": "货物运输辅助服务",
        "生产性服务业小类": "0224",
        "生产性服务业小类名称": "航空货物运输辅助活动",
        "说明": "  指机场向航空公司等服务对象提供的服务活动，空中交通管理活动和其他航空运输辅助活动",
        "国民经济行业代码": 5632,
        "国民经济行业名称": ""
    },
    {
        "生产性服务业大类": "02",
        "生产性服务业大类名称": "货物运输、通用航空生产、仓储和邮政快递服务",
        "生产性服务业中类": "022",
        "生产性服务业中类名称": "货物运输辅助服务",
        "生产性服务业小类": "0224",
        "生产性服务业小类名称": "航空货物运输辅助活动",
        "说明": "  指机场向航空公司等服务对象提供的服务活动，空中交通管理活动和其他航空运输辅助活动",
        "国民经济行业代码": 5639,
        "国民经济行业名称": ""
    },
    {
        "生产性服务业大类": "02",
        "生产性服务业大类名称": "货物运输、通用航空生产、仓储和邮政快递服务",
        "生产性服务业中类": "023",
        "生产性服务业中类名称": "  通用航空生产服务",
        "生产性服务业小类": "0230",
        "生产性服务业小类名称": "    通用航空生产服务",
        "说明": "  指通用航空为农业、测绘、航拍、抢险、救援等活动的服务，为生产活动提供的无人驾驶航空器通用航空服务以及其他未列明通用航空服务",
        "国民经济行业代码": 5621,
        "国民经济行业名称": ""
    },
    {
        "生产性服务业大类": "02",
        "生产性服务业大类名称": "货物运输、通用航空生产、仓储和邮政快递服务",
        "生产性服务业中类": "023",
        "生产性服务业中类名称": "  通用航空生产服务",
        "生产性服务业小类": "0230",
        "生产性服务业小类名称": "    通用航空生产服务",
        "说明": "  指通用航空为农业、测绘、航拍、抢险、救援等活动的服务，为生产活动提供的无人驾驶航空器通用航空服务以及其他未列明通用航空服务",
        "国民经济行业代码": "5629*",
        "国民经济行业名称": ""
    },
    {
        "生产性服务业大类": "02",
        "生产性服务业大类名称": "货物运输、通用航空生产、仓储和邮政快递服务",
        "生产性服务业中类": "024",
        "生产性服务业中类名称": "仓储服务",
        "生产性服务业小类": "0241",
        "生产性服务业小类名称": "谷物、棉花等农产品仓储",
        "说明": "  指谷物、棉花等农产品仓储",
        "国民经济行业代码": 595,
        "国民经济行业名称": ""
    },
    {
        "生产性服务业大类": "02",
        "生产性服务业大类名称": "货物运输、通用航空生产、仓储和邮政快递服务",
        "生产性服务业中类": "024",
        "生产性服务业中类名称": "仓储服务",
        "生产性服务业小类": "0242",
        "生产性服务业小类名称": "通用仓储",
        "说明": "  指除冷藏冷冻物品、危险物品、谷物、棉花、中药材等具有特殊要求以外的物品的仓储活动",
        "国民经济行业代码": 5920,
        "国民经济行业名称": ""
    },
    {
        "生产性服务业大类": "02",
        "生产性服务业大类名称": "货物运输、通用航空生产、仓储和邮政快递服务",
        "生产性服务业中类": "024",
        "生产性服务业中类名称": "仓储服务",
        "生产性服务业小类": "0243",
        "生产性服务业小类名称": "低温仓储",
        "说明": "  指对冷藏冷冻物品等低温货物的仓储活动",
        "国民经济行业代码": 5930,
        "国民经济行业名称": ""
    },
    {
        "生产性服务业大类": "02",
        "生产性服务业大类名称": "货物运输、通用航空生产、仓储和邮政快递服务",
        "生产性服务业中类": "024",
        "生产性服务业中类名称": "仓储服务",
        "生产性服务业小类": "0244",
        "生产性服务业小类名称": "危险品仓储",
        "说明": "  指对具有易燃易爆物品、危险化学品、放射性物品等能够危及人身安全和财产安全的物品的仓储活动",
        "国民经济行业代码": 594,
        "国民经济行业名称": ""
    },
    {
        "生产性服务业大类": "02",
        "生产性服务业大类名称": "货物运输、通用航空生产、仓储和邮政快递服务",
        "生产性服务业中类": "024",
        "生产性服务业中类名称": "仓储服务",
        "生产性服务业小类": "0245",
        "生产性服务业小类名称": "中药材仓储",
        "说明": "  指中草药、中成药仓储和其他中药仓储",
        "国民经济行业代码": 5960,
        "国民经济行业名称": ""
    },
    {
        "生产性服务业大类": "02",
        "生产性服务业大类名称": "货物运输、通用航空生产、仓储和邮政快递服务",
        "生产性服务业中类": "024",
        "生产性服务业中类名称": "仓储服务",
        "生产性服务业小类": "0246",
        "生产性服务业小类名称": "其他仓储业",
        "说明": "  指包装物（托盘周转箱纸箱等）运营服务，存储加工包装服务和其他未列明的仓储",
        "国民经济行业代码": 5990,
        "国民经济行业名称": ""
    },
    {
        "生产性服务业大类": "02",
        "生产性服务业大类名称": "货物运输、通用航空生产、仓储和邮政快递服务",
        "生产性服务业中类": "025",
        "生产性服务业中类名称": "搬运、包装和代理服务",
        "生产性服务业小类": "0251",
        "生产性服务业小类名称": "生产性装卸搬运",
        "说明": "  指为生产活动提供的装卸搬运",
        "国民经济行业代码": "5910*",
        "国民经济行业名称": ""
    },
    {
        "生产性服务业大类": "02",
        "生产性服务业大类名称": "货物运输、通用航空生产、仓储和邮政快递服务",
        "生产性服务业中类": "025",
        "生产性服务业中类名称": "搬运、包装和代理服务",
        "生产性服务业小类": "0252",
        "生产性服务业小类名称": "生产性包装服务",
        "说明": "  指为生产活动提供的包装服务",
        "国民经济行业代码": "7292*",
        "国民经济行业名称": ""
    },
    {
        "生产性服务业大类": "02",
        "生产性服务业大类名称": "货物运输、通用航空生产、仓储和邮政快递服务",
        "生产性服务业中类": "025",
        "生产性服务业中类名称": "搬运、包装和代理服务",
        "生产性服务业小类": "0253",
        "生产性服务业小类名称": "货物运输代理服务",
        "说明": "  指多式联运、货物运输代理和其他运输代理业",
        "国民经济行业代码": 5810,
        "国民经济行业名称": ""
    },
    {
        "生产性服务业大类": "02",
        "生产性服务业大类名称": "货物运输、通用航空生产、仓储和邮政快递服务",
        "生产性服务业中类": "025",
        "生产性服务业中类名称": "搬运、包装和代理服务",
        "生产性服务业小类": "0253",
        "生产性服务业小类名称": "货物运输代理服务",
        "说明": "  指多式联运、货物运输代理和其他运输代理业",
        "国民经济行业代码": 5821,
        "国民经济行业名称": ""
    },
    {
        "生产性服务业大类": "02",
        "生产性服务业大类名称": "货物运输、通用航空生产、仓储和邮政快递服务",
        "生产性服务业中类": "025",
        "生产性服务业中类名称": "搬运、包装和代理服务",
        "生产性服务业小类": "0253",
        "生产性服务业小类名称": "货物运输代理服务",
        "说明": "  指多式联运、货物运输代理和其他运输代理业",
        "国民经济行业代码": 5829,
        "国民经济行业名称": ""
    },
    {
        "生产性服务业大类": "02",
        "生产性服务业大类名称": "货物运输、通用航空生产、仓储和邮政快递服务",
        "生产性服务业中类": "026",
        "生产性服务业中类名称": "国家邮政和快递服务",
        "生产性服务业小类": "0261",
        "生产性服务业小类名称": "生产性邮政服务 ",
        "说明": "  指为生产活动提供的邮政服务",
        "国民经济行业代码": "6010*",
        "国民经济行业名称": ""
    },
    {
        "生产性服务业大类": "02",
        "生产性服务业大类名称": "货物运输、通用航空生产、仓储和邮政快递服务",
        "生产性服务业中类": "026",
        "生产性服务业中类名称": "国家邮政和快递服务",
        "生产性服务业小类": "0262",
        "生产性服务业小类名称": "生产性快递服务 ",
        "说明": "  指为生产活动提供的快递服务",
        "国民经济行业代码": "6020*",
        "国民经济行业名称": ""
    },
    {
        "生产性服务业大类": "02",
        "生产性服务业大类名称": "货物运输、通用航空生产、仓储和邮政快递服务",
        "生产性服务业中类": "026",
        "生产性服务业中类名称": "国家邮政和快递服务",
        "生产性服务业小类": "0263",
        "生产性服务业小类名称": "其他生产活动寄递服务",
        "说明": "  指为生产活动提供的寄递服务",
        "国民经济行业代码": "6090*",
        "国民经济行业名称": ""
    },
    {
        "生产性服务业大类": "03",
        "生产性服务业大类名称": "信息服务",
        "生产性服务业中类": "031",
        "生产性服务业中类名称": "信息传输服务",
        "生产性服务业小类": "0311",
        "生产性服务业小类名称": "生产性固定电信服务 ",
        "说明": "  指为生产活动提供的固定电信服务",
        "国民经济行业代码": "6311*",
        "国民经济行业名称": ""
    },
    {
        "生产性服务业大类": "03",
        "生产性服务业大类名称": "信息服务",
        "生产性服务业中类": "031",
        "生产性服务业中类名称": "信息传输服务",
        "生产性服务业小类": "0312",
        "生产性服务业小类名称": "生产性移动电信服务 ",
        "说明": "  指为生产活动提供的移动电信服务",
        "国民经济行业代码": "6312*",
        "国民经济行业名称": ""
    },
    {
        "生产性服务业大类": "03",
        "生产性服务业大类名称": "信息服务",
        "生产性服务业中类": "031",
        "生产性服务业中类名称": "信息传输服务",
        "生产性服务业小类": "0313",
        "生产性服务业小类名称": "其他生产活动电信服务 ",
        "说明": "  指除固定电信服务、移动电信服务外，利用固定、移动通信网为生产活动提供的信息服务，包括电信增值服务等",
        "国民经济行业代码": "6319*",
        "国民经济行业名称": ""
    },
    {
        "生产性服务业大类": "03",
        "生产性服务业大类名称": "信息服务",
        "生产性服务业中类": "032",
        "生产性服务业中类名称": "信息技术服务",
        "生产性服务业小类": "0321",
        "生产性服务业小类名称": "生产性互联网接入及相关服务 ",
        "说明": "  指生产活动中除基础电信运营商外，基于基础传输网络，为存储数据、数据处理及相关活动提供的接入互联网的有关应用设施的服务",
        "国民经济行业代码": "6410*",
        "国民经济行业名称": ""
    },
    {
        "生产性服务业大类": "03",
        "生产性服务业大类名称": "信息服务",
        "生产性服务业中类": "032",
        "生产性服务业中类名称": "信息技术服务",
        "生产性服务业小类": "0322",
        "生产性服务业小类名称": "生产性互联网信息服务",
        "说明": "  指除基础电信运营商外，通过互联网为生产提供在线信息、电子邮箱、数据检索、网络游戏、网上新闻、网上音乐等信息服务；不包括互联网支付、互联网基金销售、互联网保险、互联网信托和互联网消费金融",
        "国民经济行业代码": "642*",
        "国民经济行业名称": ""
    },
    {
        "生产性服务业大类": "03",
        "生产性服务业大类名称": "信息服务",
        "生产性服务业中类": "032",
        "生产性服务业中类名称": "信息技术服务",
        "生产性服务业小类": "0323",
        "生产性服务业小类名称": "其他互联网服务",
        "说明": "  指除基础电信运营商服务、互联网接入及相关服务、互联网信息服务以外的其他未列明互联网服务，物联网服务、农村互联网服务包含在此类",
        "国民经济行业代码": "6490*",
        "国民经济行业名称": ""
    },
    {
        "生产性服务业大类": "03",
        "生产性服务业大类名称": "信息服务",
        "生产性服务业中类": "032",
        "生产性服务业中类名称": "信息技术服务",
        "生产性服务业小类": "0324",
        "生产性服务业小类名称": "软件开发",
        "说明": "  指基础软件、支撑软件、应用软件和其他软件的开发活动",
        "国民经济行业代码": 6511,
        "国民经济行业名称": ""
    },
    {
        "生产性服务业大类": "03",
        "生产性服务业大类名称": "信息服务",
        "生产性服务业中类": "032",
        "生产性服务业中类名称": "信息技术服务",
        "生产性服务业小类": "0324",
        "生产性服务业小类名称": "软件开发",
        "说明": "  指基础软件、支撑软件、应用软件和其他软件的开发活动",
        "国民经济行业代码": 6512,
        "国民经济行业名称": ""
    },
    {
        "生产性服务业大类": "03",
        "生产性服务业大类名称": "信息服务",
        "生产性服务业中类": "032",
        "生产性服务业中类名称": "信息技术服务",
        "生产性服务业小类": "0324",
        "生产性服务业小类名称": "软件开发",
        "说明": "  指基础软件、支撑软件、应用软件和其他软件的开发活动",
        "国民经济行业代码": "6513*",
        "国民经济行业名称": ""
    },
    {
        "生产性服务业大类": "03",
        "生产性服务业大类名称": "信息服务",
        "生产性服务业中类": "032",
        "生产性服务业中类名称": "信息技术服务",
        "生产性服务业小类": "0324",
        "生产性服务业小类名称": "软件开发",
        "说明": "  指基础软件、支撑软件、应用软件和其他软件的开发活动",
        "国民经济行业代码": 6519,
        "国民经济行业名称": ""
    },
    {
        "生产性服务业大类": "03",
        "生产性服务业大类名称": "信息服务",
        "生产性服务业中类": "032",
        "生产性服务业中类名称": "信息技术服务",
        "生产性服务业小类": "0325",
        "生产性服务业小类名称": "信息技术咨询服务",
        "说明": "  指在信息资源开发利用、工程建设、人员培训、管理体系建设、技术支撑等方面向需方提供的管理或技术咨询评估服务；包括信息化规划、信息技术管理咨询、信息系统工程监理、测试评估、信息技术培训、信息安全服务等",
        "国民经济行业代码": 6560,
        "国民经济行业名称": ""
    },
    {
        "生产性服务业大类": "03",
        "生产性服务业大类名称": "信息服务",
        "生产性服务业中类": "032",
        "生产性服务业中类名称": "信息技术服务",
        "生产性服务业小类": "0326",
        "生产性服务业小类名称": "信息系统集成和物联网技术、运行维护服务",
        "说明": "  指信息系统集成服务、物联网技术服务和运行维护服务，系统解决方案服务包含在此类",
        "国民经济行业代码": 653,
        "国民经济行业名称": ""
    },
    {
        "生产性服务业大类": "03",
        "生产性服务业大类名称": "信息服务",
        "生产性服务业中类": "032",
        "生产性服务业中类名称": "信息技术服务",
        "生产性服务业小类": "0326",
        "生产性服务业小类名称": "信息系统集成和物联网技术、运行维护服务",
        "说明": "  指信息系统集成服务、物联网技术服务和运行维护服务，系统解决方案服务包含在此类",
        "国民经济行业代码": 6540,
        "国民经济行业名称": ""
    },
    {
        "生产性服务业大类": "03",
        "生产性服务业大类名称": "信息服务",
        "生产性服务业中类": "032",
        "生产性服务业中类名称": "信息技术服务",
        "生产性服务业小类": "0327",
        "生产性服务业小类名称": "集成电路设计",
        "说明": "  指IC设计服务，即企业开展的集成电路功能研发、设计等服务",
        "国民经济行业代码": 6520,
        "国民经济行业名称": ""
    },
    {
        "生产性服务业大类": "03",
        "生产性服务业大类名称": "信息服务",
        "生产性服务业中类": "032",
        "生产性服务业中类名称": "信息技术服务",
        "生产性服务业小类": "0328",
        "生产性服务业小类名称": "生产性数字内容服务",
        "说明": "  指为生产提供的地理遥感信息服务，动漫、游戏数字内容服务，其他数字内容服务",
        "国民经济行业代码": 6571,
        "国民经济行业名称": ""
    },
    {
        "生产性服务业大类": "03",
        "生产性服务业大类名称": "信息服务",
        "生产性服务业中类": "032",
        "生产性服务业中类名称": "信息技术服务",
        "生产性服务业小类": "0328",
        "生产性服务业小类名称": "生产性数字内容服务",
        "说明": "  指为生产提供的地理遥感信息服务，动漫、游戏数字内容服务，其他数字内容服务",
        "国民经济行业代码": "6572*",
        "国民经济行业名称": ""
    },
    {
        "生产性服务业大类": "03",
        "生产性服务业大类名称": "信息服务",
        "生产性服务业中类": "032",
        "生产性服务业中类名称": "信息技术服务",
        "生产性服务业小类": "0328",
        "生产性服务业小类名称": "生产性数字内容服务",
        "说明": "  指为生产提供的地理遥感信息服务，动漫、游戏数字内容服务，其他数字内容服务",
        "国民经济行业代码": "6579*",
        "国民经济行业名称": ""
    },
    {
        "生产性服务业大类": "03",
        "生产性服务业大类名称": "信息服务",
        "生产性服务业中类": "032",
        "生产性服务业中类名称": "信息技术服务",
        "生产性服务业小类": "0329",
        "生产性服务业小类名称": "其他信息技术服务业",
        "说明": "  指呼叫中心和其他未列明信息技术服务",
        "国民经济行业代码": 659,
        "国民经济行业名称": ""
    },
    {
        "生产性服务业大类": "03",
        "生产性服务业大类名称": "信息服务",
        "生产性服务业中类": "033",
        "生产性服务业中类名称": "电子商务支持服务",
        "生产性服务业小类": "0331",
        "生产性服务业小类名称": "互联网生产服务平台",
        "说明": "  指专门为生产服务提供第三方服务平台的互联网活动，包括互联网大宗商品交易平台、互联网货物运输平台等",
        "国民经济行业代码": 6431,
        "国民经济行业名称": ""
    },
    {
        "生产性服务业大类": "03",
        "生产性服务业大类名称": "信息服务",
        "生产性服务业中类": "033",
        "生产性服务业中类名称": "电子商务支持服务",
        "生产性服务业小类": "0332",
        "生产性服务业小类名称": "互联网科技创新平台",
        "说明": "  指专门为科技创新、创业等提供第三方服务平台的互联网活动，包括网络众创平台、网络众包平台、网络众扶平台、技术创新网络平台、技术交易网络平台、科技成果网络推广平台、知识产权交易平台、开源社区平台等",
        "国民经济行业代码": 6433,
        "国民经济行业名称": ""
    },
    {
        "生产性服务业大类": "03",
        "生产性服务业大类名称": "信息服务",
        "生产性服务业中类": "033",
        "生产性服务业中类名称": "电子商务支持服务",
        "生产性服务业小类": "0333",
        "生产性服务业小类名称": "互联网安全服务",
        "说明": "  指网络安全监控，以及网络服务质量、可信度和安全等评估测评活动",
        "国民经济行业代码": 6440,
        "国民经济行业名称": ""
    },
    {
        "生产性服务业大类": "03",
        "生产性服务业大类名称": "信息服务",
        "生产性服务业中类": "033",
        "生产性服务业中类名称": "电子商务支持服务",
        "生产性服务业小类": "0334",
        "生产性服务业小类名称": "互联网数据及云计算服务",
        "说明": "  指以互联网技术为基础的大数据处理、云存储、云计算、云加工等服务，包括区块链技术相关软件和服务",
        "国民经济行业代码": "6450*",
        "国民经济行业名称": ""
    },
    {
        "生产性服务业大类": "03",
        "生产性服务业大类名称": "信息服务",
        "生产性服务业中类": "033",
        "生产性服务业中类名称": "电子商务支持服务",
        "生产性服务业小类": "0335",
        "生产性服务业小类名称": "信息处理和存储支持服务",
        "说明": "  指供方向需方提供的信息和数据的分析、整理、计算、编辑、存储等加工处理服务，以及应用软件、信息系统基础设施等租用服务，包括在线企业资源规划（ERP）、在线杀毒、服务器托管、虚拟主机等",
        "国民经济行业代码": 6550,
        "国民经济行业名称": ""
    },
    {
        "生产性服务业大类": "03",
        "生产性服务业大类名称": "信息服务",
        "生产性服务业中类": "033",
        "生产性服务业中类名称": "电子商务支持服务",
        "生产性服务业小类": "0336",
        "生产性服务业小类名称": "其他互联网平台",
        "说明": "  指其他未列明的互联网平台",
        "国民经济行业代码": 6439,
        "国民经济行业名称": ""
    },
    {
        "生产性服务业大类": "03",
        "生产性服务业大类名称": "信息服务",
        "生产性服务业中类": "033",
        "生产性服务业中类名称": "电子商务支持服务",
        "生产性服务业小类": "0337",
        "生产性服务业小类名称": "生产性互联网销售",
        "说明": "  指通过互联网电子商务平台为生产活动提供的商品零售活动，企业间的网络营销活动（B2B）；不包括互联网批发、仅提供网络支付的活动，以及仅建立或提供网络交易平台和接入的活动",
        "国民经济行业代码": "5292*",
        "国民经济行业名称": ""
    },
    {
        "生产性服务业大类": "03",
        "生产性服务业大类名称": "信息服务",
        "生产性服务业中类": "033",
        "生产性服务业中类名称": "电子商务支持服务",
        "生产性服务业小类": "0338",
        "生产性服务业小类名称": "生产性非金融机构支付服务",
        "说明": "  指非金融机构在收付款人之间作为中介机构为生产活动提供的货币资金转移服务，包括第三方支付机构从事的互联网支付、预付卡的发行与受理、银行卡收单及中国人民银行确定的其他支付等服务",
        "国民经济行业代码": "6930*",
        "国民经济行业名称": ""
    },
    {
        "生产性服务业大类": "04",
        "生产性服务业大类名称": "金融服务",
        "生产性服务业中类": "041",
        "生产性服务业中类名称": "货币金融服务 ",
        "生产性服务业小类": "0411",
        "生产性服务业小类名称": "商业银行服务 ",
        "说明": "  指为生产活动提供的商业银行服务",
        "国民经济行业代码": "6621*",
        "国民经济行业名称": ""
    },
    {
        "生产性服务业大类": "04",
        "生产性服务业大类名称": "金融服务",
        "生产性服务业中类": "041",
        "生产性服务业中类名称": "货币金融服务 ",
        "生产性服务业小类": "0412",
        "生产性服务业小类名称": "信用合作社服务",
        "说明": "  指为生产活动提供的信用合作社服务",
        "国民经济行业代码": "6623*",
        "国民经济行业名称": ""
    },
    {
        "生产性服务业大类": "04",
        "生产性服务业大类名称": "金融服务",
        "生产性服务业中类": "041",
        "生产性服务业中类名称": "货币金融服务 ",
        "生产性服务业小类": "0413",
        "生产性服务业小类名称": "财务公司服务",
        "说明": "  指经银行业监督管理部门批准，为企业融资提供的金融活动",
        "国民经济行业代码": 6632,
        "国民经济行业名称": ""
    },
    {
        "生产性服务业大类": "04",
        "生产性服务业大类名称": "金融服务",
        "生产性服务业中类": "041",
        "生产性服务业中类名称": "货币金融服务 ",
        "生产性服务业小类": "0414",
        "生产性服务业小类名称": "汽车金融公司服务",
        "说明": "  指为生产活动提供的汽车金融服务",
        "国民经济行业代码": "6634*",
        "国民经济行业名称": ""
    },
    {
        "生产性服务业大类": "04",
        "生产性服务业大类名称": "金融服务",
        "生产性服务业中类": "041",
        "生产性服务业中类名称": "货币金融服务 ",
        "生产性服务业小类": "0415",
        "生产性服务业小类名称": "小额贷款公司服务",
        "说明": "  指为生产活动提供的小额贷款公司服务",
        "国民经济行业代码": "6635*",
        "国民经济行业名称": ""
    },
    {
        "生产性服务业大类": "04",
        "生产性服务业大类名称": "金融服务",
        "生产性服务业中类": "041",
        "生产性服务业中类名称": "货币金融服务 ",
        "生产性服务业小类": "0416",
        "生产性服务业小类名称": "网络借贷服务",
        "说明": "  指为生产活动提供的网络借贷服务",
        "国民经济行业代码": "6637*",
        "国民经济行业名称": ""
    },
    {
        "生产性服务业大类": "04",
        "生产性服务业大类名称": "金融服务",
        "生产性服务业中类": "041",
        "生产性服务业中类名称": "货币金融服务 ",
        "生产性服务业小类": "0417",
        "生产性服务业小类名称": "其他货币金融服务",
        "说明": "  指为生产活动提供的农村资金互助社服务，银行提供的非保本理财产品服务，其他货币银行服务和其他非货币银行服务，为节能减排提供的非银行贷款服务包含在此类",
        "国民经济行业代码": "6624*",
        "国民经济行业名称": ""
    },
    {
        "生产性服务业大类": "04",
        "生产性服务业大类名称": "金融服务",
        "生产性服务业中类": "041",
        "生产性服务业中类名称": "货币金融服务 ",
        "生产性服务业小类": "0417",
        "生产性服务业小类名称": "其他货币金融服务",
        "说明": "  指为生产活动提供的农村资金互助社服务，银行提供的非保本理财产品服务，其他货币银行服务和其他非货币银行服务，为节能减排提供的非银行贷款服务包含在此类",
        "国民经济行业代码": "6629*",
        "国民经济行业名称": ""
    },
    {
        "生产性服务业大类": "04",
        "生产性服务业大类名称": "金融服务",
        "生产性服务业中类": "041",
        "生产性服务业中类名称": "货币金融服务 ",
        "生产性服务业小类": "0417",
        "生产性服务业小类名称": "其他货币金融服务",
        "说明": "  指为生产活动提供的农村资金互助社服务，银行提供的非保本理财产品服务，其他货币银行服务和其他非货币银行服务，为节能减排提供的非银行贷款服务包含在此类",
        "国民经济行业代码": "6639*",
        "国民经济行业名称": ""
    },
    {
        "生产性服务业大类": "04",
        "生产性服务业大类名称": "金融服务",
        "生产性服务业中类": "041",
        "生产性服务业中类名称": "货币金融服务 ",
        "生产性服务业小类": "0417",
        "生产性服务业小类名称": "其他货币金融服务",
        "说明": "  指为生产活动提供的农村资金互助社服务，银行提供的非保本理财产品服务，其他货币银行服务和其他非货币银行服务，为节能减排提供的非银行贷款服务包含在此类",
        "国民经济行业代码": "6640*",
        "国民经济行业名称": ""
    },
    {
        "生产性服务业大类": "04",
        "生产性服务业大类名称": "金融服务",
        "生产性服务业中类": "041",
        "生产性服务业中类名称": "货币金融服务 ",
        "生产性服务业小类": "0418",
        "生产性服务业小类名称": "银行监管服务",
        "说明": "  指中国银行保险业监督管理委员会及分支机构的银行监管服务",
        "国民经济行业代码": 6650,
        "国民经济行业名称": ""
    },
    {
        "生产性服务业大类": "04",
        "生产性服务业大类名称": "金融服务",
        "生产性服务业中类": "042",
        "生产性服务业中类名称": "资本市场服务",
        "生产性服务业小类": "0421",
        "生产性服务业小类名称": "  证券市场服务",
        "说明": "  指证券市场管理服务和证券经纪交易服务",
        "国民经济行业代码": 671,
        "国民经济行业名称": ""
    },
    {
        "生产性服务业大类": "04",
        "生产性服务业大类名称": "金融服务",
        "生产性服务业中类": "042",
        "生产性服务业中类名称": "资本市场服务",
        "生产性服务业小类": "0422",
        "生产性服务业小类名称": "基金管理服务 ",
        "说明": "  指公开募集证券投资基金和非公开募集证券投资基金",
        "国民经济行业代码": 6720,
        "国民经济行业名称": ""
    },
    {
        "生产性服务业大类": "04",
        "生产性服务业大类名称": "金融服务",
        "生产性服务业中类": "042",
        "生产性服务业中类名称": "资本市场服务",
        "生产性服务业小类": "0422",
        "生产性服务业小类名称": "基金管理服务 ",
        "说明": "  指公开募集证券投资基金和非公开募集证券投资基金",
        "国民经济行业代码": 673,
        "国民经济行业名称": ""
    },
    {
        "生产性服务业大类": "04",
        "生产性服务业大类名称": "金融服务",
        "生产性服务业中类": "042",
        "生产性服务业中类名称": "资本市场服务",
        "生产性服务业小类": "0423",
        "生产性服务业小类名称": "期货市场服务",
        "说明": "  指期货市场管理服务和其他期货市场服务",
        "国民经济行业代码": 674,
        "国民经济行业名称": ""
    },
    {
        "生产性服务业大类": "04",
        "生产性服务业大类名称": "金融服务",
        "生产性服务业中类": "042",
        "生产性服务业中类名称": "资本市场服务",
        "生产性服务业小类": "0424",
        "生产性服务业小类名称": "资本投资服务",
        "说明": "  指经批准的证券投资机构的自营投资、直接投资活动和其他投资活动，为节能减排提供的投融资服务包含在此类",
        "国民经济行业代码": 6760,
        "国民经济行业名称": ""
    },
    {
        "生产性服务业大类": "04",
        "生产性服务业大类名称": "金融服务",
        "生产性服务业中类": "042",
        "生产性服务业中类名称": "资本市场服务",
        "生产性服务业小类": "0425",
        "生产性服务业小类名称": "其他资本服务 ",
        "说明": "  指投资咨询服务、财务咨询服务、资信评级服务，以及其他未列明的资本市场的服务",
        "国民经济行业代码": 6790,
        "国民经济行业名称": ""
    },
    {
        "生产性服务业大类": "04",
        "生产性服务业大类名称": "金融服务",
        "生产性服务业中类": "043",
        "生产性服务业中类名称": "生产性保险服务",
        "生产性服务业小类": "0431",
        "生产性服务业小类名称": "生产性财产保险 ",
        "说明": "  指为生产活动提供的财产保险服务",
        "国民经济行业代码": "6820*",
        "国民经济行业名称": ""
    },
    {
        "生产性服务业大类": "04",
        "生产性服务业大类名称": "金融服务",
        "生产性服务业中类": "043",
        "生产性服务业中类名称": "生产性保险服务",
        "生产性服务业小类": "0432",
        "生产性服务业小类名称": "生产性再保险 ",
        "说明": "  指为生产活动提供的再保险服务",
        "国民经济行业代码": "6830*",
        "国民经济行业名称": ""
    },
    {
        "生产性服务业大类": "04",
        "生产性服务业大类名称": "金融服务",
        "生产性服务业中类": "043",
        "生产性服务业中类名称": "生产性保险服务",
        "生产性服务业小类": "0433",
        "生产性服务业小类名称": "保险经纪与代理服务",
        "说明": "  指保险经纪服务和保险代理服务",
        "国民经济行业代码": 6851,
        "国民经济行业名称": ""
    },
    {
        "生产性服务业大类": "04",
        "生产性服务业大类名称": "金融服务",
        "生产性服务业中类": "043",
        "生产性服务业中类名称": "生产性保险服务",
        "生产性服务业小类": "0433",
        "生产性服务业小类名称": "保险经纪与代理服务",
        "说明": "  指保险经纪服务和保险代理服务",
        "国民经济行业代码": 6852,
        "国民经济行业名称": ""
    },
    {
        "生产性服务业大类": "04",
        "生产性服务业大类名称": "金融服务",
        "生产性服务业中类": "043",
        "生产性服务业中类名称": "生产性保险服务",
        "生产性服务业小类": "0434",
        "生产性服务业小类名称": "保险监管服务",
        "说明": "  指根据国务院授权及相关法律、法规规定所履行的对保险市场的监督、管理活动",
        "国民经济行业代码": 6870,
        "国民经济行业名称": ""
    },
    {
        "生产性服务业大类": "04",
        "生产性服务业大类名称": "金融服务",
        "生产性服务业中类": "043",
        "生产性服务业中类名称": "生产性保险服务",
        "生产性服务业小类": "0435",
        "生产性服务业小类名称": "保险公估服务",
        "说明": "  指接受委托，专门从事保险标的或者保险事故评估、勘验、鉴定、估损理算等业务，并按约定收取报酬的活动",
        "国民经济行业代码": 6853,
        "国民经济行业名称": ""
    },
    {
        "生产性服务业大类": "04",
        "生产性服务业大类名称": "金融服务",
        "生产性服务业中类": "043",
        "生产性服务业中类名称": "生产性保险服务",
        "生产性服务业小类": "0436",
        "生产性服务业小类名称": "保险资产管理",
        "说明": "  指保险资产管理公司接受委托，开展的保险资金、商业养老金等资金的投资管理活动",
        "国民经济行业代码": 6860,
        "国民经济行业名称": ""
    },
    {
        "生产性服务业大类": "04",
        "生产性服务业大类名称": "金融服务",
        "生产性服务业中类": "043",
        "生产性服务业中类名称": "生产性保险服务",
        "生产性服务业小类": "0437",
        "生产性服务业小类名称": "其他保险活动",
        "说明": "  指其他未列明的与保险和商业养老金相关或密切相关的活动，包括救助管理、保险精算等",
        "国民经济行业代码": "6890*",
        "国民经济行业名称": ""
    },
    {
        "生产性服务业大类": "04",
        "生产性服务业大类名称": "金融服务",
        "生产性服务业中类": "044",
        "生产性服务业中类名称": "其他生产性金融服务",
        "生产性服务业小类": "0441",
        "生产性服务业小类名称": "非融资担保服务",
        "说明": "  指保证人和债权人约定，当债务人不履行债务时，保证人按照约定履行债务或者承担责任的专业担保机构的活动；不包括贷款担保服务和信誉担保服务",
        "国民经济行业代码": 7296,
        "国民经济行业名称": ""
    },
    {
        "生产性服务业大类": "04",
        "生产性服务业大类名称": "金融服务",
        "生产性服务业中类": "044",
        "生产性服务业中类名称": "其他生产性金融服务",
        "生产性服务业小类": "0442",
        "生产性服务业小类名称": "金融信托与管理服务",
        "说明": "  指根据委托书、遗嘱或代理协议代表受益人管理的信托基金、房地产账户或代理账户等活动，包括单位投资信托管理，还包括信托公司通过互联网销售信托产品及开展其他信托业务的互联网信托活动",
        "国民经济行业代码": 691,
        "国民经济行业名称": ""
    },
    {
        "生产性服务业大类": "04",
        "生产性服务业大类名称": "金融服务",
        "生产性服务业中类": "044",
        "生产性服务业中类名称": "其他生产性金融服务",
        "生产性服务业小类": "0443",
        "生产性服务业小类名称": "控股公司服务",
        "说明": "  指通过一定比例股份，控制某个公司或多个公司的集团，控股公司仅控制股权，不直接参与经营管理，以及其他类似的活动",
        "国民经济行业代码": 6920,
        "国民经济行业名称": ""
    },
    {
        "生产性服务业大类": "04",
        "生产性服务业大类名称": "金融服务",
        "生产性服务业中类": "044",
        "生产性服务业中类名称": "其他生产性金融服务",
        "生产性服务业小类": "0444",
        "生产性服务业小类名称": "金融信息服务",
        "说明": "  指向从事金融分析、金融交易、金融决策或者其他金融活动的用户提供可能影响金融市场的信息（或者金融数据）的服务，包括征信机构服务",
        "国民经济行业代码": 6940,
        "国民经济行业名称": ""
    },
    {
        "生产性服务业大类": "04",
        "生产性服务业大类名称": "金融服务",
        "生产性服务业中类": "044",
        "生产性服务业中类名称": "其他生产性金融服务",
        "生产性服务业小类": "0445",
        "生产性服务业小类名称": "金融资产管理公司",
        "说明": "  指经批准成立的，以从事收购、管理和处置不良资产业务为主，同时通过全资或控股金融类子公司提供银行、信托、证券、租赁、保险等综合化金融服务的金融企业",
        "国民经济行业代码": 6950,
        "国民经济行业名称": ""
    },
    {
        "生产性服务业大类": "04",
        "生产性服务业大类名称": "金融服务",
        "生产性服务业中类": "044",
        "生产性服务业中类名称": "其他生产性金融服务",
        "生产性服务业小类": "0446",
        "生产性服务业小类名称": "其他未列明金融业",
        "说明": "  指货币经纪公司服务、其他未包括金融业；不包括为居民提供的其他金融服务",
        "国民经济行业代码": 6991,
        "国民经济行业名称": ""
    },
    {
        "生产性服务业大类": "04",
        "生产性服务业大类名称": "金融服务",
        "生产性服务业中类": "044",
        "生产性服务业中类名称": "其他生产性金融服务",
        "生产性服务业小类": "0446",
        "生产性服务业小类名称": "其他未列明金融业",
        "说明": "  指货币经纪公司服务、其他未包括金融业；不包括为居民提供的其他金融服务",
        "国民经济行业代码": "6999*",
        "国民经济行业名称": ""
    },
    {
        "生产性服务业大类": "05",
        "生产性服务业大类名称": "节能与环保服务",
        "生产性服务业中类": "051",
        "生产性服务业中类名称": "节能服务",
        "生产性服务业小类": "0511",
        "生产性服务业小类名称": "节能技术和产品推广服务",
        "说明": "  指节能技术和产品的开发、交流、转让、推广服务，以及“一站式”合同能源管理综合服务",
        "国民经济行业代码": "7514*",
        "国民经济行业名称": ""
    },
    {
        "生产性服务业大类": "05",
        "生产性服务业大类名称": "节能与环保服务",
        "生产性服务业中类": "051",
        "生产性服务业中类名称": "节能服务",
        "生产性服务业小类": "0511",
        "生产性服务业小类名称": "节能技术和产品推广服务",
        "说明": "  指节能技术和产品的开发、交流、转让、推广服务，以及“一站式”合同能源管理综合服务",
        "国民经济行业代码": "7514*",
        "国民经济行业名称": ""
    },
    {
        "生产性服务业大类": "05",
        "生产性服务业大类名称": "节能与环保服务",
        "生产性服务业中类": "051",
        "生产性服务业中类名称": "节能服务",
        "生产性服务业小类": "0512",
        "生产性服务业小类名称": "节能咨询服务",
        "说明": "  指节能技术咨询、节能评估、能源审计、节能量审核服务",
        "国民经济行业代码": "7514*",
        "国民经济行业名称": ""
    },
    {
        "生产性服务业大类": "05",
        "生产性服务业大类名称": "节能与环保服务",
        "生产性服务业中类": "052",
        "生产性服务业中类名称": "环境与污染治理服务",
        "生产性服务业小类": "0521",
        "生产性服务业小类名称": "生产性环境保护监测 ",
        "说明": "  指对生产活动产生的各类污染排放物的测试和监测服务",
        "国民经济行业代码": "7461*",
        "国民经济行业名称": ""
    },
    {
        "生产性服务业大类": "05",
        "生产性服务业大类名称": "节能与环保服务",
        "生产性服务业中类": "052",
        "生产性服务业中类名称": "环境与污染治理服务",
        "生产性服务业小类": "0522",
        "生产性服务业小类名称": "环保技术推广服务",
        "说明": "  指为解决环保技术工程的研究与试验发展活动产生的新技术、新工艺、新产品能投入生产或在实际应用中存在的技术问题而进行的系统性活动，先进环保技术推广服务，绿色低碳技术咨询服务，脱硫、脱硝除尘一体化技术推广服务，清洁生产技术咨询服务",
        "国民经济行业代码": 7516,
        "国民经济行业名称": ""
    },
    {
        "生产性服务业大类": "05",
        "生产性服务业大类名称": "节能与环保服务",
        "生产性服务业中类": "052",
        "生产性服务业中类名称": "环境与污染治理服务",
        "生产性服务业小类": "0523",
        "生产性服务业小类名称": "生产性污水处理和水污染治理",
        "说明": "  指对生产活动产生的污水进行处理和水污染治理",
        "国民经济行业代码": "4620*",
        "国民经济行业名称": ""
    },
    {
        "生产性服务业大类": "05",
        "生产性服务业大类名称": "节能与环保服务",
        "生产性服务业中类": "052",
        "生产性服务业中类名称": "环境与污染治理服务",
        "生产性服务业小类": "0523",
        "生产性服务业小类名称": "生产性污水处理和水污染治理",
        "说明": "  指对生产活动产生的污水进行处理和水污染治理",
        "国民经济行业代码": "7721*",
        "国民经济行业名称": ""
    },
    {
        "生产性服务业大类": "05",
        "生产性服务业大类名称": "节能与环保服务",
        "生产性服务业中类": "052",
        "生产性服务业中类名称": "环境与污染治理服务",
        "生产性服务业小类": "0524",
        "生产性服务业小类名称": "生产性大气污染治理 ",
        "说明": "  指对生产活动产生的废气进行的污染治理",
        "国民经济行业代码": "7722*",
        "国民经济行业名称": ""
    },
    {
        "生产性服务业大类": "05",
        "生产性服务业大类名称": "节能与环保服务",
        "生产性服务业中类": "052",
        "生产性服务业中类名称": "环境与污染治理服务",
        "生产性服务业小类": "0525",
        "生产性服务业小类名称": "生产性固体废物治理 ",
        "说明": "  指除城乡居民生活垃圾以外的，对生产活动产生的固体废物治理及其他非危险废物的治理",
        "国民经济行业代码": "7723*",
        "国民经济行业名称": ""
    },
    {
        "生产性服务业大类": "05",
        "生产性服务业大类名称": "节能与环保服务",
        "生产性服务业中类": "052",
        "生产性服务业中类名称": "环境与污染治理服务",
        "生产性服务业小类": "0526",
        "生产性服务业小类名称": "生产性危险废物治理 ",
        "说明": "  指对制造、维修、医疗等活动产生的危险废物进行收集、贮存、利用、处理和处置等活动",
        "国民经济行业代码": 7724,
        "国民经济行业名称": ""
    },
    {
        "生产性服务业大类": "05",
        "生产性服务业大类名称": "节能与环保服务",
        "生产性服务业中类": "052",
        "生产性服务业中类名称": "环境与污染治理服务",
        "生产性服务业小类": "0527",
        "生产性服务业小类名称": "生产性放射性废物治理 ",
        "说明": "  指对生产过程中产生的放射性废物的治理",
        "国民经济行业代码": "7725*",
        "国民经济行业名称": ""
    },
    {
        "生产性服务业大类": "05",
        "生产性服务业大类名称": "节能与环保服务",
        "生产性服务业中类": "052",
        "生产性服务业中类名称": "环境与污染治理服务",
        "生产性服务业小类": "0528",
        "生产性服务业小类名称": "生产性其他污染治理 ",
        "说明": "  指为生产活动提供的土壤污染治理与修复服务、噪声与振动控制服务、其他污染治理",
        "国民经济行业代码": "7726*",
        "国民经济行业名称": ""
    },
    {
        "生产性服务业大类": "05",
        "生产性服务业大类名称": "节能与环保服务",
        "生产性服务业中类": "052",
        "生产性服务业中类名称": "环境与污染治理服务",
        "生产性服务业小类": "0528",
        "生产性服务业小类名称": "生产性其他污染治理 ",
        "说明": "  指为生产活动提供的土壤污染治理与修复服务、噪声与振动控制服务、其他污染治理",
        "国民经济行业代码": "7727*",
        "国民经济行业名称": ""
    },
    {
        "生产性服务业大类": "05",
        "生产性服务业大类名称": "节能与环保服务",
        "生产性服务业中类": "052",
        "生产性服务业中类名称": "环境与污染治理服务",
        "生产性服务业小类": "0528",
        "生产性服务业小类名称": "生产性其他污染治理 ",
        "说明": "  指为生产活动提供的土壤污染治理与修复服务、噪声与振动控制服务、其他污染治理",
        "国民经济行业代码": "7729*",
        "国民经济行业名称": ""
    },
    {
        "生产性服务业大类": "05",
        "生产性服务业大类名称": "节能与环保服务",
        "生产性服务业中类": "053",
        "生产性服务业中类名称": "回收与利用服务",
        "生产性服务业小类": "0530",
        "生产性服务业小类名称": "再生物资回收与批发",
        "说明": "  指将可再生的废旧物资回收，并批发给制造企业作初级原料的活动",
        "国民经济行业代码": 5191,
        "国民经济行业名称": ""
    },
    {
        "生产性服务业大类": "06",
        "生产性服务业大类名称": "生产性租赁服务",
        "生产性服务业中类": "061",
        "生产性服务业中类名称": "融资租赁服务",
        "生产性服务业小类": "0610",
        "生产性服务业小类名称": "融资租赁服务",
        "说明": "  指经中国银行保险监督管理委员会批准的金融租赁公司及经地方金融监管部门批准的融资租赁公司的活动",
        "国民经济行业代码": 6631,
        "国民经济行业名称": ""
    },
    {
        "生产性服务业大类": "06",
        "生产性服务业大类名称": "生产性租赁服务",
        "生产性服务业中类": "062",
        "生产性服务业中类名称": "实物租赁服务",
        "生产性服务业小类": "0621",
        "生产性服务业小类名称": "生产性汽车租赁",
        "说明": "  指为生产活动提供的汽车租赁活动",
        "国民经济行业代码": "7111*",
        "国民经济行业名称": ""
    },
    {
        "生产性服务业大类": "06",
        "生产性服务业大类名称": "生产性租赁服务",
        "生产性服务业中类": "062",
        "生产性服务业中类名称": "实物租赁服务",
        "生产性服务业小类": "0622",
        "生产性服务业小类名称": "农业机械经营租赁",
        "说明": "  指拖拉机、播种机、收割机、脱谷机等机械设备出租活动",
        "国民经济行业代码": 7112,
        "国民经济行业名称": ""
    },
    {
        "生产性服务业大类": "06",
        "生产性服务业大类名称": "生产性租赁服务",
        "生产性服务业中类": "062",
        "生产性服务业中类名称": "实物租赁服务",
        "生产性服务业小类": "0623",
        "生产性服务业小类名称": "建筑工程机械与设备经营租赁",
        "说明": "  指推土机、压路机、自卸运土车、混泥土搅拌机、塔吊、脚锁架等机械和设备的出租活动",
        "国民经济行业代码": 7113,
        "国民经济行业名称": ""
    },
    {
        "生产性服务业大类": "06",
        "生产性服务业大类名称": "生产性租赁服务",
        "生产性服务业中类": "062",
        "生产性服务业中类名称": "实物租赁服务",
        "生产性服务业小类": "0624",
        "生产性服务业小类名称": "计算机及通讯设备经营租赁",
        "说明": "  指计算机及辅助设备（打印机、扫描仪等）租赁、通信设备租赁服务",
        "国民经济行业代码": 7114,
        "国民经济行业名称": ""
    },
    {
        "生产性服务业大类": "06",
        "生产性服务业大类名称": "生产性租赁服务",
        "生产性服务业中类": "062",
        "生产性服务业中类名称": "实物租赁服务",
        "生产性服务业小类": "0625",
        "生产性服务业小类名称": "医疗设备经营租赁",
        "说明": "  指医用X射线设备、医用超声诊断、医用电气诊断、医用激光诊断等治疗仪器及设备的租赁服务",
        "国民经济行业代码": 7115,
        "国民经济行业名称": ""
    },
    {
        "生产性服务业大类": "06",
        "生产性服务业大类名称": "生产性租赁服务",
        "生产性服务业中类": "062",
        "生产性服务业中类名称": "实物租赁服务",
        "生产性服务业小类": "0626",
        "生产性服务业小类名称": "其他机械与设备经营租赁",
        "说明": "  指铁路运输设备、水上运输设备、空中运输设备、集装箱、办公设备及其他未列明机械设备租赁服务，环保设备租赁包含在此类",
        "国民经济行业代码": 7119,
        "国民经济行业名称": ""
    },
    {
        "生产性服务业大类": "07",
        "生产性服务业大类名称": "商务服务",
        "生产性服务业中类": "071",
        "生产性服务业中类名称": "组织管理和综合管理服务",
        "生产性服务业小类": "0711",
        "生产性服务业小类名称": "企业总部管理",
        "说明": "  指不具体从事对外经营业务，只负责企业的重大决策、资产管理，协调管理下属各机构和内部日常工作的企业总部的活动，其对外经营业务由下属的独立核算单位或单独核算单位承担，还包括派出机构的活动（如办事处等）",
        "国民经济行业代码": 7211,
        "国民经济行业名称": ""
    },
    {
        "生产性服务业大类": "07",
        "生产性服务业大类名称": "商务服务",
        "生产性服务业中类": "071",
        "生产性服务业中类名称": "组织管理和综合管理服务",
        "生产性服务业小类": "0712",
        "生产性服务业小类名称": "投资与资产管理",
        "说明": "  指政府主管部门转变职能后成立的国有资产管理机构和行业管理机构的活动，其他投资管理活动；不包括资本投资服务",
        "国民经济行业代码": 7212,
        "国民经济行业名称": ""
    },
    {
        "生产性服务业大类": "07",
        "生产性服务业大类名称": "商务服务",
        "生产性服务业中类": "071",
        "生产性服务业中类名称": "组织管理和综合管理服务",
        "生产性服务业小类": "0713",
        "生产性服务业小类名称": "资源与产权交易服务",
        "说明": "  指除货物、资本市场、黄金、外汇、房地产、土地、知识产权交易以外的所有资源与产权交易活动，产权交易、废弃物交易、碳排放交易包含在此类",
        "国民经济行业代码": 7213,
        "国民经济行业名称": ""
    },
    {
        "生产性服务业大类": "07",
        "生产性服务业大类名称": "商务服务",
        "生产性服务业中类": "071",
        "生产性服务业中类名称": "组织管理和综合管理服务",
        "生产性服务业小类": "0714",
        "生产性服务业小类名称": "单位后勤管理服务",
        "说明": "  指为企事业、机关提供综合后勤服务的活动",
        "国民经济行业代码": 7214,
        "国民经济行业名称": ""
    },
    {
        "生产性服务业大类": "07",
        "生产性服务业大类名称": "商务服务",
        "生产性服务业中类": "071",
        "生产性服务业中类名称": "组织管理和综合管理服务",
        "生产性服务业小类": "0715",
        "生产性服务业小类名称": "农村集体经济组织管理",
        "说明": "  指以土地等生产资料劳动群众集体所有制为基础，承担管理集体资产、开发集体资源、发展集体经济、服务集体成员的基层经济组织",
        "国民经济行业代码": 7215,
        "国民经济行业名称": ""
    },
    {
        "生产性服务业大类": "07",
        "生产性服务业大类名称": "商务服务",
        "生产性服务业中类": "071",
        "生产性服务业中类名称": "组织管理和综合管理服务",
        "生产性服务业小类": "0716",
        "生产性服务业小类名称": "其他组织管理服务",
        "说明": "  指为生产活动提供的其他各类企业、行业管理机构和未列明的综合跨界管理的活动",
        "国民经济行业代码": "7219*",
        "国民经济行业名称": ""
    },
    {
        "生产性服务业大类": "07",
        "生产性服务业大类名称": "商务服务",
        "生产性服务业中类": "071",
        "生产性服务业中类名称": "组织管理和综合管理服务",
        "生产性服务业小类": "0717",
        "生产性服务业小类名称": "园区和商业综合体管理服务",
        "说明": "  指非政府部门的各类园区管理服务，商业综合体管理服务",
        "国民经济行业代码": 7221,
        "国民经济行业名称": ""
    },
    {
        "生产性服务业大类": "07",
        "生产性服务业大类名称": "商务服务",
        "生产性服务业中类": "071",
        "生产性服务业中类名称": "组织管理和综合管理服务",
        "生产性服务业小类": "0717",
        "生产性服务业小类名称": "园区和商业综合体管理服务",
        "说明": "  指非政府部门的各类园区管理服务，商业综合体管理服务",
        "国民经济行业代码": "7222*",
        "国民经济行业名称": ""
    },
    {
        "生产性服务业大类": "07",
        "生产性服务业大类名称": "商务服务",
        "生产性服务业中类": "071",
        "生产性服务业中类名称": "组织管理和综合管理服务",
        "生产性服务业小类": "0718",
        "生产性服务业小类名称": "供应链管理服务",
        "说明": "  指基于现代信息技术对供应链中的物流、商流、信息流和资金流进行设计、规划、控制和优化，将单一、分散的订单管理、采购执行、报关退税、物流管理、资金融通、数据管理、贸易商务、结算等进行一体化整合的服务",
        "国民经济行业代码": 7224,
        "国民经济行业名称": ""
    },
    {
        "生产性服务业大类": "07",
        "生产性服务业大类名称": "商务服务",
        "生产性服务业中类": "071",
        "生产性服务业中类名称": "组织管理和综合管理服务",
        "生产性服务业小类": "0719",
        "生产性服务业小类名称": "其他综合性管理服务",
        "说明": "  指为生产活动提供的其他综合跨界管理的活动",
        "国民经济行业代码": "7229*",
        "国民经济行业名称": ""
    },
    {
        "生产性服务业大类": "07",
        "生产性服务业大类名称": "商务服务",
        "生产性服务业中类": "072",
        "生产性服务业中类名称": "咨询与调查服务",
        "生产性服务业小类": "0721",
        "生产性服务业小类名称": "会计、审计及税务服务",
        "说明": "  资产评估、清算服务，以及能源审计服务包含在此类",
        "国民经济行业代码": 7241,
        "国民经济行业名称": ""
    },
    {
        "生产性服务业大类": "07",
        "生产性服务业大类名称": "商务服务",
        "生产性服务业中类": "072",
        "生产性服务业中类名称": "咨询与调查服务",
        "生产性服务业小类": "0722",
        "生产性服务业小类名称": "市场调查",
        "说明": "  指市场分析调查服务、统计调查服务、社会及民意调查服务、其他市场调查服务",
        "国民经济行业代码": 7242,
        "国民经济行业名称": ""
    },
    {
        "生产性服务业大类": "07",
        "生产性服务业大类名称": "商务服务",
        "生产性服务业中类": "072",
        "生产性服务业中类名称": "咨询与调查服务",
        "生产性服务业小类": "0723",
        "生产性服务业小类名称": "商务咨询服务",
        "说明": "  指为生产活动提供的社会经济咨询、健康咨询、环保咨询、体育咨询和其他专业咨询与调查，包括物流方案策划、物流咨询、发展战略规划、营销策划、管理咨询；不包括全民健身咨询",
        "国民经济行业代码": 7243,
        "国民经济行业名称": ""
    },
    {
        "生产性服务业大类": "07",
        "生产性服务业大类名称": "商务服务",
        "生产性服务业中类": "072",
        "生产性服务业中类名称": "咨询与调查服务",
        "生产性服务业小类": "0723",
        "生产性服务业小类名称": "商务咨询服务",
        "说明": "  指为生产活动提供的社会经济咨询、健康咨询、环保咨询、体育咨询和其他专业咨询与调查，包括物流方案策划、物流咨询、发展战略规划、营销策划、管理咨询；不包括全民健身咨询",
        "国民经济行业代码": "7244*",
        "国民经济行业名称": ""
    },
    {
        "生产性服务业大类": "07",
        "生产性服务业大类名称": "商务服务",
        "生产性服务业中类": "072",
        "生产性服务业中类名称": "咨询与调查服务",
        "生产性服务业小类": "0723",
        "生产性服务业小类名称": "商务咨询服务",
        "说明": "  指为生产活动提供的社会经济咨询、健康咨询、环保咨询、体育咨询和其他专业咨询与调查，包括物流方案策划、物流咨询、发展战略规划、营销策划、管理咨询；不包括全民健身咨询",
        "国民经济行业代码": 7245,
        "国民经济行业名称": ""
    },
    {
        "生产性服务业大类": "07",
        "生产性服务业大类名称": "商务服务",
        "生产性服务业中类": "072",
        "生产性服务业中类名称": "咨询与调查服务",
        "生产性服务业小类": "0723",
        "生产性服务业小类名称": "商务咨询服务",
        "说明": "  指为生产活动提供的社会经济咨询、健康咨询、环保咨询、体育咨询和其他专业咨询与调查，包括物流方案策划、物流咨询、发展战略规划、营销策划、管理咨询；不包括全民健身咨询",
        "国民经济行业代码": "7246*",
        "国民经济行业名称": ""
    },
    {
        "生产性服务业大类": "07",
        "生产性服务业大类名称": "商务服务",
        "生产性服务业中类": "072",
        "生产性服务业中类名称": "咨询与调查服务",
        "生产性服务业小类": "0723",
        "生产性服务业小类名称": "商务咨询服务",
        "说明": "  指为生产活动提供的社会经济咨询、健康咨询、环保咨询、体育咨询和其他专业咨询与调查，包括物流方案策划、物流咨询、发展战略规划、营销策划、管理咨询；不包括全民健身咨询",
        "国民经济行业代码": "7249*",
        "国民经济行业名称": ""
    },
    {
        "生产性服务业大类": "07",
        "生产性服务业大类名称": "商务服务",
        "生产性服务业中类": "073",
        "生产性服务业中类名称": "其他生产性商务服务",
        "生产性服务业小类": "0731",
        "生产性服务业小类名称": "广告业",
        "说明": "  指在报纸、期刊、路牌、灯箱、橱窗、互联网、通讯设备及广播电影电视等媒介上为客户策划、制作的有偿宣传活动",
        "国民经济行业代码": 725,
        "国民经济行业名称": ""
    },
    {
        "生产性服务业大类": "07",
        "生产性服务业大类名称": "商务服务",
        "生产性服务业中类": "073",
        "生产性服务业中类名称": "其他生产性商务服务",
        "生产性服务业小类": "0732",
        "生产性服务业小类名称": "生产性安全保护服务 ",
        "说明": "  指为生产活动提供的保安服务、安全系统监控服务等",
        "国民经济行业代码": "727*",
        "国民经济行业名称": ""
    },
    {
        "生产性服务业大类": "07",
        "生产性服务业大类名称": "商务服务",
        "生产性服务业中类": "073",
        "生产性服务业中类名称": "其他生产性商务服务",
        "生产性服务业小类": "0733",
        "生产性服务业小类名称": "生产性市场管理服务",
        "说明": "  指为生产活动提供的各种交易市场的管理活动",
        "国民经济行业代码": "7223*",
        "国民经济行业名称": ""
    },
    {
        "生产性服务业大类": "07",
        "生产性服务业大类名称": "商务服务",
        "生产性服务业中类": "073",
        "生产性服务业中类名称": "其他生产性商务服务",
        "生产性服务业小类": "0734",
        "生产性服务业小类名称": "会议、展览及相关服务",
        "说明": "  指以会议、展览为主，也可附带其他相关的活动形式，包括项目策划组织、场馆租赁、保障服务等",
        "国民经济行业代码": 728,
        "国民经济行业名称": ""
    },
    {
        "生产性服务业大类": "07",
        "生产性服务业大类名称": "商务服务",
        "生产性服务业中类": "073",
        "生产性服务业中类名称": "其他生产性商务服务",
        "生产性服务业小类": "0735",
        "生产性服务业小类名称": "办公和翻译服务",
        "说明": "  指为商务、公务提供的各种办公服务和翻译服务",
        "国民经济行业代码": "7293*",
        "国民经济行业名称": ""
    },
    {
        "生产性服务业大类": "07",
        "生产性服务业大类名称": "商务服务",
        "生产性服务业中类": "073",
        "生产性服务业中类名称": "其他生产性商务服务",
        "生产性服务业小类": "0735",
        "生产性服务业小类名称": "办公和翻译服务",
        "说明": "  指为商务、公务提供的各种办公服务和翻译服务",
        "国民经济行业代码": 7294,
        "国民经济行业名称": ""
    },
    {
        "生产性服务业大类": "07",
        "生产性服务业大类名称": "商务服务",
        "生产性服务业中类": "073",
        "生产性服务业中类名称": "其他生产性商务服务",
        "生产性服务业小类": "0736",
        "生产性服务业小类名称": "信用服务",
        "说明": "  指专门从事信用信息采集、整理和加工，并提供相关信用产品和信用服务的活动，包括信用评级、商账管理等活动",
        "国民经济行业代码": 7295,
        "国民经济行业名称": ""
    },
    {
        "生产性服务业大类": "07",
        "生产性服务业大类名称": "商务服务",
        "生产性服务业中类": "073",
        "生产性服务业中类名称": "其他生产性商务服务",
        "生产性服务业小类": "0737",
        "生产性服务业小类名称": "其他未列明生产性商务服务",
        "说明": "  指为生产活动提供的商务代理代办服务，票务代理服务，文化活动服务，体育表演服务和其他未列明商务服务；不包括人力资源服务和为居民提供的包装服务",
        "国民经济行业代码": 7297,
        "国民经济行业名称": ""
    },
    {
        "生产性服务业大类": "07",
        "生产性服务业大类名称": "商务服务",
        "生产性服务业中类": "073",
        "生产性服务业中类名称": "其他生产性商务服务",
        "生产性服务业小类": "0737",
        "生产性服务业小类名称": "其他未列明生产性商务服务",
        "说明": "  指为生产活动提供的商务代理代办服务，票务代理服务，文化活动服务，体育表演服务和其他未列明商务服务；不包括人力资源服务和为居民提供的包装服务",
        "国民经济行业代码": 7298,
        "国民经济行业名称": ""
    },
    {
        "生产性服务业大类": "07",
        "生产性服务业大类名称": "商务服务",
        "生产性服务业中类": "073",
        "生产性服务业中类名称": "其他生产性商务服务",
        "生产性服务业小类": "0737",
        "生产性服务业小类名称": "其他未列明生产性商务服务",
        "说明": "  指为生产活动提供的商务代理代办服务，票务代理服务，文化活动服务，体育表演服务和其他未列明商务服务；不包括人力资源服务和为居民提供的包装服务",
        "国民经济行业代码": 7299,
        "国民经济行业名称": ""
    },
    {
        "生产性服务业大类": "07",
        "生产性服务业大类名称": "商务服务",
        "生产性服务业中类": "073",
        "生产性服务业中类名称": "其他生产性商务服务",
        "生产性服务业小类": "0737",
        "生产性服务业小类名称": "其他未列明生产性商务服务",
        "说明": "  指为生产活动提供的商务代理代办服务，票务代理服务，文化活动服务，体育表演服务和其他未列明商务服务；不包括人力资源服务和为居民提供的包装服务",
        "国民经济行业代码": 9051,
        "国民经济行业名称": ""
    },
    {
        "生产性服务业大类": "07",
        "生产性服务业大类名称": "商务服务",
        "生产性服务业中类": "073",
        "生产性服务业中类名称": "其他生产性商务服务",
        "生产性服务业小类": "0737",
        "生产性服务业小类名称": "其他未列明生产性商务服务",
        "说明": "  指为生产活动提供的商务代理代办服务，票务代理服务，文化活动服务，体育表演服务和其他未列明商务服务；不包括人力资源服务和为居民提供的包装服务",
        "国民经济行业代码": 9052,
        "国民经济行业名称": ""
    },
    {
        "生产性服务业大类": "08",
        "生产性服务业大类名称": "人力资源管理与职业教育培训服务",
        "生产性服务业中类": "081",
        "生产性服务业中类名称": "人力资源管理",
        "生产性服务业小类": "0811",
        "生产性服务业小类名称": "职业中介服务",
        "说明": "  指为求职者寻找、选择、介绍工作，为用人单位提供劳动力的服务",
        "国民经济行业代码": 7262,
        "国民经济行业名称": ""
    },
    {
        "生产性服务业大类": "08",
        "生产性服务业大类名称": "人力资源管理与职业教育培训服务",
        "生产性服务业中类": "081",
        "生产性服务业中类名称": "人力资源管理",
        "生产性服务业小类": "0812",
        "生产性服务业小类名称": "劳务派遣服务",
        "说明": "  指劳务派遣单位招用劳动力后，将其派到用工单位从事劳动的行为",
        "国民经济行业代码": 7263,
        "国民经济行业名称": ""
    },
    {
        "生产性服务业大类": "08",
        "生产性服务业大类名称": "人力资源管理与职业教育培训服务",
        "生产性服务业中类": "081",
        "生产性服务业中类名称": "人力资源管理",
        "生产性服务业小类": "0813",
        "生产性服务业小类名称": "创业指导服务",
        "说明": "  指除众创空间、孵化器等创业服务载体外的其他机构为初创企业或创业者提供的创业辅导、创业培训、技术转移、人才引进、金融投资、市场开拓、国际合作等一系列服务",
        "国民经济行业代码": 7264,
        "国民经济行业名称": ""
    },
    {
        "生产性服务业大类": "08",
        "生产性服务业大类名称": "人力资源管理与职业教育培训服务",
        "生产性服务业中类": "081",
        "生产性服务业中类名称": "人力资源管理",
        "生产性服务业小类": "0814",
        "生产性服务业小类名称": "其他人力资源服务",
        "说明": "  指其他未列明的人力资源服务",
        "国民经济行业代码": 7269,
        "国民经济行业名称": ""
    },
    {
        "生产性服务业大类": "08",
        "生产性服务业大类名称": "人力资源管理与职业教育培训服务",
        "生产性服务业中类": "082",
        "生产性服务业中类名称": "职业教育和培训",
        "生产性服务业小类": "0821",
        "生产性服务业小类名称": "职业初中教育",
        "说明": "  指为生产活动提供的职业初中教育",
        "国民经济行业代码": "8332*",
        "国民经济行业名称": ""
    },
    {
        "生产性服务业大类": "08",
        "生产性服务业大类名称": "人力资源管理与职业教育培训服务",
        "生产性服务业中类": "082",
        "生产性服务业中类名称": "职业教育和培训",
        "生产性服务业小类": "0822",
        "生产性服务业小类名称": "中等职业学校教育",
        "说明": "  指为生产活动提供的中等职业学校教育",
        "国民经济行业代码": "8336*",
        "国民经济行业名称": ""
    },
    {
        "生产性服务业大类": "08",
        "生产性服务业大类名称": "人力资源管理与职业教育培训服务",
        "生产性服务业中类": "082",
        "生产性服务业中类名称": "职业教育和培训",
        "生产性服务业小类": "0823",
        "生产性服务业小类名称": "高等职业学校教育",
        "说明": "  指为生产活动提供的高等职业学校教育",
        "国民经济行业代码": "8341*",
        "国民经济行业名称": ""
    },
    {
        "生产性服务业大类": "08",
        "生产性服务业大类名称": "人力资源管理与职业教育培训服务",
        "生产性服务业中类": "082",
        "生产性服务业中类名称": "职业教育和培训",
        "生产性服务业小类": "0824",
        "生产性服务业小类名称": "职业技能培训",
        "说明": "  指为生产活动提供的就业前技能培训和其他技能培训活动；不包括社会上办的各类培训班、速成班、讲座等；农业技术培训等包含在此类",
        "国民经济行业代码": "8391*",
        "国民经济行业名称": ""
    },
    {
        "生产性服务业大类": "09",
        "生产性服务业大类名称": "批发与贸易经纪代理服务",
        "生产性服务业中类": "091",
        "生产性服务业中类名称": "产品批发服务",
        "生产性服务业小类": "0911",
        "生产性服务业小类名称": "农、林、牧、渔产品及宠物食品用品批发 ",
        "说明": "  指未经过加工的农作物产品（或种植业产品）、林产品及牲畜、畜产品、奶、水产品、鱼苗、宠物食品用品的批发和进出口活动，但不包括蔬菜、水果、肉、禽、蛋的批发和进出口活动，包括以批发为目的的农副产品收购活动",
        "国民经济行业代码": 511,
        "国民经济行业名称": ""
    },
    {
        "生产性服务业大类": "09",
        "生产性服务业大类名称": "批发与贸易经纪代理服务",
        "生产性服务业中类": "091",
        "生产性服务业中类名称": "产品批发服务",
        "生产性服务业小类": "0911",
        "生产性服务业小类名称": "农、林、牧、渔产品及宠物食品用品批发 ",
        "说明": "  指未经过加工的农作物产品（或种植业产品）、林产品及牲畜、畜产品、奶、水产品、鱼苗、宠物食品用品的批发和进出口活动，但不包括蔬菜、水果、肉、禽、蛋的批发和进出口活动，包括以批发为目的的农副产品收购活动",
        "国民经济行业代码": 5192,
        "国民经济行业名称": ""
    },
    {
        "生产性服务业大类": "09",
        "生产性服务业大类名称": "批发与贸易经纪代理服务",
        "生产性服务业中类": "091",
        "生产性服务业中类名称": "产品批发服务",
        "生产性服务业小类": "0912",
        "生产性服务业小类名称": "食品、饮料及烟草制品批发",
        "说明": "  指经过加工和制造的食品、饮料、奶、水产品及烟草制品的批发和进出口活动，以及蔬菜、水果、肉、禽、蛋的批发和进出口活动",
        "国民经济行业代码": 512,
        "国民经济行业名称": ""
    },
    {
        "生产性服务业大类": "09",
        "生产性服务业大类名称": "批发与贸易经纪代理服务",
        "生产性服务业中类": "091",
        "生产性服务业中类名称": "产品批发服务",
        "生产性服务业小类": "0913",
        "生产性服务业小类名称": "纺织、服装及家庭用品批发",
        "说明": "  指纺织面料、纺织品、服装、鞋、帽及日杂品、家用电器、家具等生活日用品的批发和进出口活动",
        "国民经济行业代码": 513,
        "国民经济行业名称": ""
    },
    {
        "生产性服务业大类": "09",
        "生产性服务业大类名称": "批发与贸易经纪代理服务",
        "生产性服务业中类": "091",
        "生产性服务业中类名称": "产品批发服务",
        "生产性服务业小类": "0914",
        "生产性服务业小类名称": "文化、体育用品及器材批发",
        "说明": "  指各类文具用品、体育用品、图书、报刊、音像制品、电子出版物、数字出版物、首饰、工艺美术品、收藏品及其他文化用品、器材的批发和进出口活动",
        "国民经济行业代码": 514,
        "国民经济行业名称": ""
    },
    {
        "生产性服务业大类": "09",
        "生产性服务业大类名称": "批发与贸易经纪代理服务",
        "生产性服务业中类": "091",
        "生产性服务业中类名称": "产品批发服务",
        "生产性服务业小类": "0915",
        "生产性服务业小类名称": "医药及医疗器材批发",
        "说明": "  指各种化学药品、生物药品、中药及医疗器材的批发和进出口活动，包括兽用药的批发和进出口活动",
        "国民经济行业代码": 515,
        "国民经济行业名称": ""
    },
    {
        "生产性服务业大类": "09",
        "生产性服务业大类名称": "批发与贸易经纪代理服务",
        "生产性服务业中类": "091",
        "生产性服务业中类名称": "产品批发服务",
        "生产性服务业小类": "0916",
        "生产性服务业小类名称": "矿产品、建材及化工产品批发",
        "说明": "  指煤及煤制品、石油制品、矿产品及矿物制品、金属材料、建筑和装饰装修材料以及化工产品的批发和进出口活动",
        "国民经济行业代码": 516,
        "国民经济行业名称": ""
    },
    {
        "生产性服务业大类": "09",
        "生产性服务业大类名称": "批发与贸易经纪代理服务",
        "生产性服务业中类": "091",
        "生产性服务业中类名称": "产品批发服务",
        "生产性服务业小类": "0917",
        "生产性服务业小类名称": "机械设备、五金产品及电子产品批发",
        "说明": "  指通用机械、专用设备、交通运输设备、电气机械、五金、交通器材、电料、计算机设备、通讯设备、电子产品、仪器仪表及办公用机械的批发和进出口活动",
        "国民经济行业代码": 517,
        "国民经济行业名称": ""
    },
    {
        "生产性服务业大类": "09",
        "生产性服务业大类名称": "批发与贸易经纪代理服务",
        "生产性服务业中类": "091",
        "生产性服务业中类名称": "产品批发服务",
        "生产性服务业小类": "0918",
        "生产性服务业小类名称": "互联网批发",
        "说明": "  指通过互联网电子商务平台开展的商品批发活动",
        "国民经济行业代码": 5193,
        "国民经济行业名称": ""
    },
    {
        "生产性服务业大类": "09",
        "生产性服务业大类名称": "批发与贸易经纪代理服务",
        "生产性服务业中类": "091",
        "生产性服务业中类名称": "产品批发服务",
        "生产性服务业小类": "0919",
        "生产性服务业小类名称": "其他未列明批发业",
        "说明": "  指木炭、薪柴等其他未列明的批发活动",
        "国民经济行业代码": 5199,
        "国民经济行业名称": ""
    },
    {
        "生产性服务业大类": "09",
        "生产性服务业大类名称": "批发与贸易经纪代理服务",
        "生产性服务业中类": "092",
        "生产性服务业中类名称": "贸易经纪代理服务",
        "生产性服务业小类": "0921",
        "生产性服务业小类名称": "贸易代理",
        "说明": "  指不拥有货物的所有权，为实现供求双方达成交易，按协议收取佣金的贸易代理",
        "国民经济行业代码": 5181,
        "国民经济行业名称": ""
    },
    {
        "生产性服务业大类": "09",
        "生产性服务业大类名称": "批发与贸易经纪代理服务",
        "生产性服务业中类": "092",
        "生产性服务业中类名称": "贸易经纪代理服务",
        "生产性服务业小类": "0922",
        "生产性服务业小类名称": "一般物品拍卖",
        "说明": "  指大宗物品拍卖服务、行政、司法拍卖服务、其他拍卖服务",
        "国民经济行业代码": 5182,
        "国民经济行业名称": ""
    },
    {
        "生产性服务业大类": "09",
        "生产性服务业大类名称": "批发与贸易经纪代理服务",
        "生产性服务业中类": "092",
        "生产性服务业中类名称": "贸易经纪代理服务",
        "生产性服务业小类": "0923",
        "生产性服务业小类名称": "艺术品、收藏品拍卖",
        "说明": "  指艺（美）术品拍卖服务，文物拍卖服务，古董、字画拍卖服务",
        "国民经济行业代码": 5183,
        "国民经济行业名称": ""
    },
    {
        "生产性服务业大类": "09",
        "生产性服务业大类名称": "批发与贸易经纪代理服务",
        "生产性服务业中类": "092",
        "生产性服务业中类名称": "贸易经纪代理服务",
        "生产性服务业小类": "0924",
        "生产性服务业小类名称": "艺术品代理",
        "说明": "  指艺术品、收藏品销售代理，以及画廊艺术经纪代理",
        "国民经济行业代码": 5184,
        "国民经济行业名称": ""
    },
    {
        "生产性服务业大类": "09",
        "生产性服务业大类名称": "批发与贸易经纪代理服务",
        "生产性服务业中类": "092",
        "生产性服务业中类名称": "贸易经纪代理服务",
        "生产性服务业小类": "0925",
        "生产性服务业小类名称": "其他贸易经纪与代理",
        "说明": "  指寄卖等其他贸易经纪与代理",
        "国民经济行业代码": 5189,
        "国民经济行业名称": ""
    },
    {
        "生产性服务业大类": "10",
        "生产性服务业大类名称": "生产性支持服务",
        "生产性服务业中类": "101",
        "生产性服务业中类名称": "农林牧渔专业及辅助性活动",
        "生产性服务业小类": "1011",
        "生产性服务业小类名称": "农业专业及辅助性活动",
        "说明": "  指对农业提供的各种专业及辅助性生产活动；不包括各种科学技术和专业技术服务",
        "国民经济行业代码": 51,
        "国民经济行业名称": ""
    },
    {
        "生产性服务业大类": "10",
        "生产性服务业大类名称": "生产性支持服务",
        "生产性服务业中类": "101",
        "生产性服务业中类名称": "农林牧渔专业及辅助性活动",
        "生产性服务业小类": "1012",
        "生产性服务业小类名称": "林业专业及辅助性活动",
        "说明": "  指为林业生产提供的林业有害生物防治、林地防火等各种辅助性活动",
        "国民经济行业代码": 52,
        "国民经济行业名称": ""
    },
    {
        "生产性服务业大类": "10",
        "生产性服务业大类名称": "生产性支持服务",
        "生产性服务业中类": "101",
        "生产性服务业中类名称": "农林牧渔专业及辅助性活动",
        "生产性服务业小类": "1013",
        "生产性服务业小类名称": "畜牧专业及辅助性活动",
        "说明": "  指提供牲畜繁殖、圈舍清理、畜产品生产、初级加工、动物免疫接种、标识佩戴和动物诊疗等活动",
        "国民经济行业代码": 53,
        "国民经济行业名称": ""
    },
    {
        "生产性服务业大类": "10",
        "生产性服务业大类名称": "生产性支持服务",
        "生产性服务业中类": "101",
        "生产性服务业中类名称": "农林牧渔专业及辅助性活动",
        "生产性服务业小类": "1014",
        "生产性服务业小类名称": "渔业专业及辅助性活动",
        "说明": "  指对渔业生产提供的各种活动，包括鱼苗及鱼种场、水产良种场和水产增殖场等活动",
        "国民经济行业代码": 54,
        "国民经济行业名称": ""
    },
    {
        "生产性服务业大类": "10",
        "生产性服务业大类名称": "生产性支持服务",
        "生产性服务业中类": "102",
        "生产性服务业中类名称": "开采专业及辅助性活动",
        "生产性服务业小类": "1021",
        "生产性服务业小类名称": "煤炭开采和洗选专业及辅助性活动",
        "说明": "  指煤炭的勘探服务，煤矿的排水和泵吸活动，煤矿的试井与试钻",
        "国民经济行业代码": 1110,
        "国民经济行业名称": ""
    },
    {
        "生产性服务业大类": "10",
        "生产性服务业大类名称": "生产性支持服务",
        "生产性服务业中类": "102",
        "生产性服务业中类名称": "开采专业及辅助性活动",
        "生产性服务业小类": "1022",
        "生产性服务业小类名称": "石油和天然气开采专业及辅助性活动",
        "说明": "  指石油和天然气开采相关的勘探活动，定向钻井和再钻，掘进，井架的架设、修复和拆除，油气井套管的胶接，油气井的泵送，油气井的封堵和放弃等，排水和泵吸活动，与石油或天然气开采相关的试钻",
        "国民经济行业代码": 1120,
        "国民经济行业名称": ""
    },
    {
        "生产性服务业大类": "10",
        "生产性服务业大类名称": "生产性支持服务",
        "生产性服务业中类": "102",
        "生产性服务业中类名称": "开采专业及辅助性活动",
        "生产性服务业小类": "1023",
        "生产性服务业小类名称": "其他开采专业及辅助性活动",
        "说明": "  指其他矿的勘探服务，在收费或合同基础上进行的其他矿的排水和泵吸活动，其他矿的试井与试钻",
        "国民经济行业代码": 1190,
        "国民经济行业名称": ""
    },
    {
        "生产性服务业大类": "10",
        "生产性服务业大类名称": "生产性支持服务",
        "生产性服务业中类": "103",
        "生产性服务业中类名称": "为生产人员提供的支助服务 ",
        "生产性服务业小类": "1031",
        "生产性服务业小类名称": "为生产人员提供的交通服务",
        "说明": "  指为生产、商务活动提供铁路、公路、水上、民航的旅客运输，以及城市公共交通运输服务",
        "国民经济行业代码": "531*",
        "国民经济行业名称": ""
    },
    {
        "生产性服务业大类": "10",
        "生产性服务业大类名称": "生产性支持服务",
        "生产性服务业中类": "103",
        "生产性服务业中类名称": "为生产人员提供的支助服务 ",
        "生产性服务业小类": "1031",
        "生产性服务业小类名称": "为生产人员提供的交通服务",
        "说明": "  指为生产、商务活动提供铁路、公路、水上、民航的旅客运输，以及城市公共交通运输服务",
        "国民经济行业代码": "541*",
        "国民经济行业名称": ""
    },
    {
        "生产性服务业大类": "10",
        "生产性服务业大类名称": "生产性支持服务",
        "生产性服务业中类": "103",
        "生产性服务业中类名称": "为生产人员提供的支助服务 ",
        "生产性服务业小类": "1031",
        "生产性服务业小类名称": "为生产人员提供的交通服务",
        "说明": "  指为生产、商务活动提供铁路、公路、水上、民航的旅客运输，以及城市公共交通运输服务",
        "国民经济行业代码": "542*",
        "国民经济行业名称": ""
    },
    {
        "生产性服务业大类": "10",
        "生产性服务业大类名称": "生产性支持服务",
        "生产性服务业中类": "103",
        "生产性服务业中类名称": "为生产人员提供的支助服务 ",
        "生产性服务业小类": "1031",
        "生产性服务业小类名称": "为生产人员提供的交通服务",
        "说明": "  指为生产、商务活动提供铁路、公路、水上、民航的旅客运输，以及城市公共交通运输服务",
        "国民经济行业代码": "551*",
        "国民经济行业名称": ""
    },
    {
        "生产性服务业大类": "10",
        "生产性服务业大类名称": "生产性支持服务",
        "生产性服务业中类": "103",
        "生产性服务业中类名称": "为生产人员提供的支助服务 ",
        "生产性服务业小类": "1031",
        "生产性服务业小类名称": "为生产人员提供的交通服务",
        "说明": "  指为生产、商务活动提供铁路、公路、水上、民航的旅客运输，以及城市公共交通运输服务",
        "国民经济行业代码": "5611*",
        "国民经济行业名称": ""
    },
    {
        "生产性服务业大类": "10",
        "生产性服务业大类名称": "生产性支持服务",
        "生产性服务业中类": "103",
        "生产性服务业中类名称": "为生产人员提供的支助服务 ",
        "生产性服务业小类": "1032",
        "生产性服务业小类名称": "为生产人员提供的其他支助服务",
        "说明": "  指为生产、商务活动提供旅游饭店、一般旅馆的住宿服务和体检服务",
        "国民经济行业代码": "6110*",
        "国民经济行业名称": ""
    },
    {
        "生产性服务业大类": "10",
        "生产性服务业大类名称": "生产性支持服务",
        "生产性服务业中类": "103",
        "生产性服务业中类名称": "为生产人员提供的支助服务 ",
        "生产性服务业小类": "1032",
        "生产性服务业小类名称": "为生产人员提供的其他支助服务",
        "说明": "  指为生产、商务活动提供旅游饭店、一般旅馆的住宿服务和体检服务",
        "国民经济行业代码": "612*",
        "国民经济行业名称": ""
    },
    {
        "生产性服务业大类": "10",
        "生产性服务业大类名称": "生产性支持服务",
        "生产性服务业中类": "103",
        "生产性服务业中类名称": "为生产人员提供的支助服务 ",
        "生产性服务业小类": "1032",
        "生产性服务业小类名称": "为生产人员提供的其他支助服务",
        "说明": "  指为生产、商务活动提供旅游饭店、一般旅馆的住宿服务和体检服务",
        "国民经济行业代码": "6190*",
        "国民经济行业名称": ""
    },
    {
        "生产性服务业大类": "10",
        "生产性服务业大类名称": "生产性支持服务",
        "生产性服务业中类": "103",
        "生产性服务业中类名称": "为生产人员提供的支助服务 ",
        "生产性服务业小类": "1032",
        "生产性服务业小类名称": "为生产人员提供的其他支助服务",
        "说明": "  指为生产、商务活动提供旅游饭店、一般旅馆的住宿服务和体检服务",
        "国民经济行业代码": "8491*",
        "国民经济行业名称": ""
    },
    {
        "生产性服务业大类": "10",
        "生产性服务业大类名称": "生产性支持服务",
        "生产性服务业中类": "104",
        "生产性服务业中类名称": "机械设备修理和售后服务",
        "生产性服务业小类": "1041",
        "生产性服务业小类名称": "金属制品、机械和设备修理业",
        "说明": "  指金属制品、通用设备和专用设备的修理活动",
        "国民经济行业代码": 43,
        "国民经济行业名称": ""
    },
    {
        "生产性服务业大类": "10",
        "生产性服务业大类名称": "生产性支持服务",
        "生产性服务业中类": "104",
        "生产性服务业中类名称": "机械设备修理和售后服务",
        "生产性服务业小类": "1042",
        "生产性服务业小类名称": "生产用汽车修理与维护",
        "说明": "  指为生产活动提供的汽车维修和维护服务",
        "国民经济行业代码": "8111*",
        "国民经济行业名称": ""
    },
    {
        "生产性服务业大类": "10",
        "生产性服务业大类名称": "生产性支持服务",
        "生产性服务业中类": "104",
        "生产性服务业中类名称": "机械设备修理和售后服务",
        "生产性服务业小类": "1043",
        "生产性服务业小类名称": "生产用大型车辆装备修理与维护",
        "说明": "  指为生产活动提供的大型车辆装备维修和维护服务",
        "国民经济行业代码": "8112*",
        "国民经济行业名称": ""
    },
    {
        "生产性服务业大类": "10",
        "生产性服务业大类名称": "生产性支持服务",
        "生产性服务业中类": "104",
        "生产性服务业中类名称": "机械设备修理和售后服务",
        "生产性服务业小类": "1044",
        "生产性服务业小类名称": "生产用摩托车修理与维护",
        "说明": "  指为生产活动提供的摩托车修理与维护活动",
        "国民经济行业代码": "8113*",
        "国民经济行业名称": ""
    },
    {
        "生产性服务业大类": "10",
        "生产性服务业大类名称": "生产性支持服务",
        "生产性服务业中类": "104",
        "生产性服务业中类名称": "机械设备修理和售后服务",
        "生产性服务业小类": "1045",
        "生产性服务业小类名称": "生产用助动车修理与维护",
        "说明": "  指为生产活动提供的助动车修理与维护活动",
        "国民经济行业代码": "8114*",
        "国民经济行业名称": ""
    },
    {
        "生产性服务业大类": "10",
        "生产性服务业大类名称": "生产性支持服务",
        "生产性服务业中类": "104",
        "生产性服务业中类名称": "机械设备修理和售后服务",
        "生产性服务业小类": "1046",
        "生产性服务业小类名称": "生产用计算机和办公设备维修",
        "说明": "  指为生产活动提供的计算机和辅助设备修理，通讯设备修理，其他办公设备维修，电子办公设备的三包等售后服务包含在此类",
        "国民经济行业代码": "8121*",
        "国民经济行业名称": ""
    },
    {
        "生产性服务业大类": "10",
        "生产性服务业大类名称": "生产性支持服务",
        "生产性服务业中类": "104",
        "生产性服务业中类名称": "机械设备修理和售后服务",
        "生产性服务业小类": "1046",
        "生产性服务业小类名称": "生产用计算机和办公设备维修",
        "说明": "  指为生产活动提供的计算机和辅助设备修理，通讯设备修理，其他办公设备维修，电子办公设备的三包等售后服务包含在此类",
        "国民经济行业代码": "8122*",
        "国民经济行业名称": ""
    },
    {
        "生产性服务业大类": "10",
        "生产性服务业大类名称": "生产性支持服务",
        "生产性服务业中类": "104",
        "生产性服务业中类名称": "机械设备修理和售后服务",
        "生产性服务业小类": "1046",
        "生产性服务业小类名称": "生产用计算机和办公设备维修",
        "说明": "  指为生产活动提供的计算机和辅助设备修理，通讯设备修理，其他办公设备维修，电子办公设备的三包等售后服务包含在此类",
        "国民经济行业代码": 8129,
        "国民经济行业名称": ""
    },
    {
        "生产性服务业大类": "10",
        "生产性服务业大类名称": "生产性支持服务",
        "生产性服务业中类": "104",
        "生产性服务业中类名称": "机械设备修理和售后服务",
        "生产性服务业小类": "1047",
        "生产性服务业小类名称": "生产用电器修理 ",
        "说明": "  指为生产活动提供的电器维修及其他三包售后服务",
        "国民经济行业代码": "813*",
        "国民经济行业名称": ""
    },
    {
        "生产性服务业大类": "10",
        "生产性服务业大类名称": "生产性支持服务",
        "生产性服务业中类": "105",
        "生产性服务业中类名称": "生产性保洁服务",
        "生产性服务业小类": "1051",
        "生产性服务业小类名称": "建筑物清洁服务",
        "说明": "  指对建筑物内外墙、玻璃幕墙、地面、天花板及烟囱的清洗活动",
        "国民经济行业代码": 8211,
        "国民经济行业名称": ""
    },
    {
        "生产性服务业大类": "10",
        "生产性服务业大类名称": "生产性支持服务",
        "生产性服务业中类": "105",
        "生产性服务业中类名称": "生产性保洁服务",
        "生产性服务业小类": "1052",
        "生产性服务业小类名称": "其他生产性清洁服务",
        "说明": "指专业清洗人员为企业的机器、办公设备的清洗活动",
        "国民经济行业代码": "8219*",
        "国民经济行业名称": ""
    }
]